Workbook

Sheet column_info_dataentry
A1: Language | B1: Recorder name | C1: Language | D1: Reference no | E1: Study region | F1: Area name | G1: Kingdom | H1: Taxonomic resolution | I1: Taxonomic unit | J1: Taxonomic unit_revised | K1: Ecosystem | L1: Information source | M1: Gradient | N1: Position | O1: Measurement type | P1: Start period | Q1: End period | R1: N years | S1: Number of censuses | T1: Magnitude of shift | U1: Unit of shift | V1: Azimuth of shift | W1: Shift tested | X1: Shift significant | Y1: Data cleaning | Z1: Modelling conducted | AA1: Other effects | AB1: Shift source | AC1: Notes
A2: EN Multiple-choice format Fill-in-the-blank format | B2: Name of the person recording the entry record | C2: Language that the paper was written in: EN/JA | D2: Reference no | E2: Study region: Japan/Region/Prefecture | F2: Specific name of the study area: e.g. island name, national park name. This might be useful for mapping the study locations later on. | G2: Kingdom of target organism: Animal/Plant/Others | H2: The finest level of the taxonomic resolution used: Species-level/Genus-level/Family-level/Order-level. This might be useful because not all studies report at the species-level. | I2: If finest taxonomic resolution is at the species-level, record Latin name of target organism (e.g. Salvelinus leucomaenis). If it is at other levels, record the name of that taxonomic group (e.g. Fabaceae family). | J2: Cross-reference the taxonomic names within the “Taxonomy unit” against authoritative taxonomic lists. Where inappropriate, please amend the name and record the correct designation here. The following databases are recommended: Marine >> World Register of Marine Species Alpine, Forest, Grassland, River >> CheckListBank | K2: Targeted ecosystem: Marine/Freshwater/Forest/Grassland/Alpine/Other (please specify which ecosystem like Other: wetlands) | L2: How were the resurvey data obtained? Authors did the resurvey/GBIF/Citizen science/etc. | M2: Gradient of the measured shift: Elevation/Depth/Latitude/Longitude/Horizontal We can recompute latitude or longitude shift based on the magnitude of horizontal shift and the bearing/azimuth, using trigonometric. | N2: Study sites position: Leading edge/Centroid/Trailing edge/Unknown of the distribution | O2: Observation mesurement: Occurrence/Abundance | P2: AD The year or the time period corresponding to the baseline data used to assess the range position of the target taxa. (e.g., year 1970, time period 1970-1980) | Q2: AD The year or the time period corresponding to the last resurvey from which the authors assessed the range position of the target taxa. (e.g., year 2010, time period 2010-2020) | R2: Number of years The duration in number of years of the period for which the shift is calculated | S2: Number of censuses How many surveys were performed in the study | T2: How large is the shift in numerical value (shown in conjunction with the ”Unit of shift”). Consider the direction of shift (either positive or negative) when recording. Shifting towards higher elevations, poleward, or towards deeper depth in aquatic systems, respectively, is considered positive, and negative otherwise. For instance, 500 m elevational increase should be anotated 500, but a shift of 200 m downslope should be anotated -200. In terms of longitudinal shifts, eastward should be anotated as positive values while westward should be anotated as negative values | U2: The unit of the shift: meter, km, degrees | V2: Azimuth (angle) of shift in degrees (North is 0 or 360, East is 90, South is 180, West is 270). This is rarely reported, but worth recording when authors report only the horizontal shifts, together with the bearing/azymuth/angle without decomposing it into latitudinal and longitudional shifts. | W2: Whether a statistical test was conducted to assess the significance of the shift at the taxonomic unit level? Yes/No | X2: Is the shift significant ? Yes (significant shift)/No (not significant shift)/NA (not analized) | Y2: Authors use the raw data to compute the range shifts without cleaning (No) or use the cleaned data for the range shift computation (Yes): Yes/No | Z2: Authors compute the range shifts from the modelled range positions (Yes) or compute the shift from raw data (No): Yes/No, Examples of model approaches are logistic regression, random forest, etc. | AA2: Potential causes of range shifts other than temperature alone (land use changes/invasive species/pollution/precipitation changes/etc.) | AB2: For each shift recorded, indicate whether it was stated (numerically) in the paper or estimated from figures. If the shift amount was not provided in the paper, calculate it using user-friendly free software. Record the name of the software used in "Note". | AC2: Add any information needed to clarify the data entries in the different fields
A3: JP 選択肢式 記入式 | B3: 記録者名 | C3: 文献が書かれた言語：EN/JA | D3: 文献番号 | E3: 対象地域：日本全域/地方/都道府県 | F3: 具体的な地名：地域名、島名、国立公園名など。いずれ全体で再調査の場所を地図化するときに便利。 | G3: 対象とした生物界：動物/植物/その他 | H3: 使用されている分類学的解像度のうち最も細かいレベル：種レベル/属レベル/科レベル/目レベル。必ずしも種レベルで報告されていないことも考慮するため。 | I3: 種レベルで報告されている場合は対象とした生物の学名（例 Salvelinus leucomaenis）。他のレベルの場合は、その分類群名（例：マメ科）。 | J3: 「Taxonomi unit」内の分類学名を権威ある分類学リストと照合し、不適切な場合、名称を修正し正しい名称をここに記してください。次のデータベースをお勧めします。 Marine >> World Register of Marine Species Alpine, Forest, Grassland, River >> CheckListBank | K3: 対象とした生態系：海洋/河川/森林/草地/高山/その他（具体的にどの生態系か分かるように、その他：湿地、などと書いてください）。 | L3: 再調査データの取得方法。著者が再調査を実施/GBIF/市民科学など | M3: 分布変化を調べた傾度、方向性：標高/深さ/緯度/経度/水平方向 三角法を用いれば、水平方向の変位量と方位角から緯度/経度の変位量を再計算できる | N3: 研究対象地の位置：分布域の前縁/重心/後縁/不明 に位置する | O3: 観測値：在不在/生物量 | P3: 観測開始年または期間（西暦）対象分類群の分布状況を評価するために用いられた基準データに対応する年または期間（例：年なら1970、期間なら1970-1980） | Q3: 観測終了年または期間（西暦）対象分類群の分布状況を評価した最後の再調査に対応する年または期間。（例：年なら2010、期間なら2010-2020） | R3: シフトが計算される期間の長さ（年数） | S3: 調査回数：実施された調査の回数 | T3: 変化の大きさ(Unit of shiftとセットで示す)：数値。記録時には変動方向（正または負）を考慮すること。標高が高い方向、極方向、水系では深部方向への変動は正とみなされ、それ以外は負とする。例えば、標高500mの上昇は500と記録するが、200mの下り斜面への移動は-200と記録する。経度方向の移動では、東方向は正の値、西方向は負の値として記録する | U3: 変化の単位：メートル、キロメートル、度 | V3: 経度方向の変化の方位角（北を0、東90、南180、西270と考える）。めったに報告されていないが、記録しておくといい。 | W3: 分布のシフトが有意であるかを調べる統計解析が行われたか：Yes/No | X3: シフトは有意か？ : No（有意なシフトなし）/Yes（有意なシフト）/No analyses(解析無し) | Y3: 生データを用いて分布域の移動量を計算している か(No)、データクリーニングを実施してから分布域の移動量を計算しているか(Yes)：Yes/No | Z3: モデルを用いて分布位置を評価してから分布の移動量を計算しているか(Yes）、生データから移動量を計算しているか(No)：Yes/No。モデルはlogistic regressionやrandom forestなどのことを指す。 | AA3: 気温以外の潜在的要因（土地利用変化/外来種/汚染/…） | AB3: 記録された各シフトについて、それが論文に数値で記載されていたか(stated)、図から推定されたか(estimated)を明記してください。 論文にシフト量が記載されていない場合は、使いやすい無料ソフトウェアを使用して計算してください。使用したソフトウェアの名前を「注記」欄に記録してください。 | AC3: 各フィールドのデータ入力内容を明確化するために必要な情報を追加してください。
B4: Nana | C4: JA

Sheet column_info_EnJalist
A1: Language | B1: Reference no | C1: group | D1: article_title | E1: abstract | F1: match_finalresult | G1: Recorder name | H1: Match_Target | I1: Right_Ecosystem | J1: Match_Target_final | K1: Data_section | L1: Comments | M1: source_title | N1: publication_year | O1: authors | P1: doi | Q1: doi of accepted paper
A2: EN | B2: Unique ID for each research paper. If you know a paper that fits this review but not on the list, please add them to this list. Use your initials and numbers to create a unique ID for each paper (e.g., E_TS1). Then, extract the data into the "dataentry" sheet. Papers listed in a previous comprehensive review are added to this list as well (i.e., E_ogawa11) | C2: Which ecosystem the paper is about and thus the group that will read the paper: Marine/Freshwater/Forest/Grassland/Alpine In case the ecosystem classification is incorrect, note the right ecosytem in the Right_Ecosystem column. | D2: Title of the paper. | E2: Abstract of the paper. | F2: Result after the first screening process (Title and abstract screening by ChatGPT + Double check for omission error by human based on titles). Papers that were classified as "yes" or "maybe" qualify for the second screening step, and thus are listed here. | G2: who will read the paper in the group | H2: Whether the paper qualifies for full-text screening after reading the title and abstract: Yes/Maybe/No/Duplicated | I2: If the paper is classified in the wrong ecosystem, please note the correct ecosystem here: Marine/Freshwater/Forest/Grassland/Alpine/Other (please specify which ecosystem) | J2: Whether the paper qualifies after full-text screening: Yes/No "Yes" papers are the ones that contain quantitative info on species range shifts, which will be extracted into the "dataentry" sheet. | K2: From which section of the paper was the info extracted? E.g., Text/Fig 1/Table 2 | L2: Any comments. E.g., reasons for/against qualification, duplication/not able to download/etc. | M2: Title of journal, book, etc. | N2: Year of publication. | O2: Name of authors. | P2: DOI of the paper (URL if DOI is not found) | Q2: If the paper was a preprint and the official article is published, please note the DOI of the published paper here. This is to avoid duplication since the published paper can also be in the list. If the paper is published but not in the list, please add it to the list since data extracted from the published paper is more reliable. In case the article is not published, extract data from the preprint.
A3: JP | B3: 各研究論文の固有ID。 本レビューに該当する論文でリストにないものがあれば、このリストに追加してください。各論文に固有IDを付与するため、イニシャルと数字を使用してください（例：E_TS1）。その後、データを「dataentry」シートに抽出してください。 過去の包括的レビューに掲載された論文も本リストに追加します（例：E_ogawa11） | C3: 本論文が対象とする生態系、および論文を読むグループ：海洋／淡水／森林／草原／高山 生態系の分類が誤っている場合は、正しい生態系をRight_Ecosystem欄に記入してください。 | E3: 論文の要旨 | F3: 一次審査後の結果（ChatGPTによるタイトル・抄録審査＋人間によるタイトルに基づく脱落誤りの再確認）。「はい」または「可能性あり」と分類された論文は二次審査対象となり、ここにリストアップされています。 | G3: グループで誰がこの論文を読むのか | H3: タイトルと抄録を読んだ結果、論文が全文スクリーニングの対象となるか：はい／おそらく／いいえ／重複 | J3: 全文スクリーニングした結果、この論文が適格か：はい／いいえ 「はい」と判定された論文は、種の分布域変動に関する定量的な情報を含むものであり、これらは「データ入力」シートに抽出される。 | K3: 情報はどのセクションから抽出しましたか？ 例：本文／図1／表2 | L3: コメント 例：適格性の理由／不適格の理由、重複／ダウンロード不可など。 | M3: 雑誌や書籍のタイトル | N3: 発行年 | O3: 著者名 | P3: 論文のDOI（DOIが見つからない場合はURL） | Q3: 論文がプレプリントであり正式な論文が公開された場合、公開論文のDOIをここに記入してください。公開論文もリストに含まれる可能性があるため、重複を避けるためです。論文が公開されているがリストにない場合は、公開論文から抽出したデータの方が信頼性が高いため、リストに追加してください。論文が公開されていない場合は、プレプリントからデータを抽出してください。

Sheet En-list_editing
A1: Comment when merging & cleaning | B1: Reference no prev | C1: Reference no editing | D1: Reference no | E1: group | F1: article_title | G1: abstract | H1: match_finalresult | I1: Recorder name | J1: Match_Target | K1: Right_Ecosystem | L1: Match_Target_final | M1: Data_section | N1: Comments | O1: source_title | P1: publication_year | Q1: authors | R1: doi | S1: doi of accepted paper
B2: E_TSakiyama1 | C2: =LEFT(B2,1) & TEXT(RIGHT(B2,LEN(B2)-1),"0000") -> E_TSakiyama1 | D2: E_saki1 | E2: alpine | F2: The advancing timberline on Mt. Fuji: natural recovery or climate change? | G2: The alpine timberline on Mt. Fuji (central Japan) is at 2,400–2,500 m above sea level. Over a 21-year period (1978–1999), we tracked changes in this vegetation boundary on a transect at a site impacted by the 1707 volcanic eruption. The timberline advanced rapidly upwards during this time period. Dominant tree species at the timberline (Alnus maximowiczii, Salix reinii, and Larix kaempferi) colonized sites that were initially largely free of vegetation at higher altitudes. Seedlings of L. kaempferi were particularly abundant at the border of advancing vegetation. According to tree age, we found that this was the first canopy species in the colonized areas. L. kaempferi is drought resistant, and this probably contributes to its establishment capability in the high-altitude climate. Most seedlings of Abies veitchii invaded patches of herbs and shrubs. These vegetation patches in the upper kampfzone provide important shelter for seedlings of invading tree species. We predict that the upward advance of the alpine timberline is a recovery process following the volcanic eruption, and that climate change may accelerate this advance. | H2: yes | I2: Sakiyama | J2: yes | K2: Alpine | L2: Yes | M2: Fig. 4 | N2: The study concludes that the advancing timberline is a natural recovery process rather than climate change effects, but this study is included because climate change is discussed to have an accelerating effect in this natural recovery process. | O2: Journal of Plant Research | P2: 2012 | Q2: Sakio & Masuzawa | R2: https://doi.org/10.1007/s10265-011-0465-3
B3: E1 | C3: =LEFT(B3,1) & TEXT(RIGHT(B3,LEN(B3)-1),"0000") -> E0001 | D3: E0001 | E3: alpine | F3: Climate change impact assessment on mountain snow hydrology by water and energy budget-based distributed hydrological model | G3: A water and energy budget-based distributed hydrological model with improved snow physics (WEB-DHM-S) was applied to elucidate the impact of climate change on mountain snow hydrology in the Shubuto River basin, Hokkaido, Japan. The simulated spatial distribution of snow cover was evaluated using the Moderate Resolution Imaging Spectroradiometer (MODIS) 8-day maximum snow-cover extent (MOD10A2) product, which revealed the model's capability for capturing the spatiotemporal variations in snow cover within the study area. Four Atmosphere Ocean General Circulation Models (A0GCMs) were selected and the SRESA1B emission scenario of the Intergovernmental Panel on Climate Change was used to describe climate predictions in the basin. All AOGCMs predict a future decrease in snowmelt contribution to total discharge 11-22% and an average decrease in SWE of 36%, with a shift in peak SWE by 4-14 days. The shift in runoff regime is broadly consistent between the AOGCMs with snowmelt-induced peak discharge expected to occur on average about two weeks earlier in the future hydrological year. The warming climate will drive a shift in runoff regime from a combined rainfall- and snowmelt-driven regime to one with a reduced contribution from snowmelt. The results of the study revealed that the model could be successfully applicable on the basin scale to simulate river discharge and snow processes and to investigate the effect of climate change on hydrological processes. This research contributes to improve the understanding of basin hydrological responses and the pace of change associated with climate variability. (C) 2016 Elsevier B.V. All rights reserved. | H3: yes | I3: Sakiyama | J3: No | N3: The paper is about snow hydrology. | O3: Journal of hydrology | P3: 2016 | Q3: Bhatti, AM; Koike, T; Shrestha, M | R3: 10.1016/j.jhydrol.2016.10.025
B4: E5 | C4: =LEFT(B4,1) & TEXT(RIGHT(B4,LEN(B4)-1),"0000") -> E0005 | D4: E0005 | E4: alpine | F4: Evolutionary history of a cold-adapted limnephilid caddisfly: effects of climate change and topography on genetic structure | G4: The distribution of organisms is influenced by complex factors such as the phylogenetic evolutionary histories of species, the physiological and ecological characteristics of organisms, climate, and geographical and geohistorical features. In this study, we focused on a caddisfly, Asynarchus sachalinensis (Trichoptera: Limnephilidae), which has adapted to cold habitats. From phylogeographic analyses based on the mitochondrial DNA (mtDNA) cytochrome c oxidase subunit I (COI) and 16S rRNA regions and the nuclear DNA (nDNA) 18S rRNA, 28S rRNA, carbamoyl-phosphate synthetase (CAD), elongation factor-1 alpha (EF1-alpha), and RNA polymerase II (POLII) regions, two distinct genetic clades were detected. Clade I was shown to be widely distributed from Sakhalin to Honshu, whereas Clade II was only distributed within Honshu. The distributions of these clades overlapped in Honshu. The habitats were located at relatively lower altitudes for Clade I and higher altitudes for Clade II. The divergence time of these clades was estimated to be during the Pleistocene, indicating that repeated climatic changes facilitated distributional shifts. Haplotype network and demographic analyses based on the mtDNA COI region showed contrasting genetic structures in the two clades. It was indicated that the population sizes of Clade I had expanded rapidly in a recent period, whereas Clade II had maintained stable population sizes. The habitats of Clade II were typically isolated and scattered at high altitudes, resulting in restricted migration and dispersal because of their discontinuous Sky Island habitats. The habitats of Clade I were located at relatively low altitudes, and it was assumed that the populations were continuous, which resulted in a higher frequency of migration and dispersal between populations. Thus, differences in the spatial scale of the adapted habitats of each clade may have resulted in different patterns of population connectivity and fragmentation associated with repeated climatic changes during the Pleistocene. Our study provided new insight into the distributional patterns of cold-adapted aquatic insects in the Japanese Archipelago. Furthermore, the distributional shifts predicted by ecological niche modeling under future climatic change conditions were different for each clade. Therefore, different principles are required in the assessment of each clade to predict temporal changes in their distributions. | H4: yes | I4: Sakiyama | J4: No | N4: The paper is about phylogenetics. | O4: Molecular phylogenetics and evolution | P4: 2024 | Q4: Suzuki, H; Takenaka, M; Tojo, K | R4: 10.1016/j.ympev.2023.107967
B5: E9 | C5: =LEFT(B5,1) & TEXT(RIGHT(B5,LEN(B5)-1),"0000") -> E0009 | D5: E0009 | E5: alpine | F5: Latitudinal shifts in the distribution of exploited fishes in korean waters during the last 30 years: a consequence of climate change | G5: Sea surface temperatures in Korean waters have increased by approximately 1 degrees C during the past 40 years, implying possible range shifts of marine fishes and invertebrates. We analyzed spatially explicit, commercial catch data for 12 major fish species collected from 1984 to 2010 in Korean waters to evaluate and project their range shifts based on climate-driven hydrographic changes simulated by a general circulation model under a climate change scenario. There were significant relationships between the mean latitude of the catch distribution and water temperature for seven of the 12 species examined. Our circulation model projected that temperature stratification in the Korea Strait will disappear by 2030, and our empirical relationships predicted that the ranges of five of the fish species examined will shift poleward by 19-71 km from the 2000s to the 2030s. Compared with studies of demersal fishes in the western North Atlantic and the North Sea, our estimated speeds of shift in mean latitude of fishes were, on average, slower by factors of 2.3 and 5.7, respectively. This suggests that the pattern of range shift of marine species can vary regionally, depending on oceanographic and geomorphologic conditions. International cooperative research among fisheries scientists from countries throughout the region, especially Japan and China, is required to more reliably and comprehensively assess and project the range shifts of fish species. This will provide a scientific basis for the development of fishery policies and their adaptation to climate change in the western North Pacific. | H5: yes | I5: Sakiyama | J5: Maybe | K5: Marine | L5: Yes? | M5: Fig. 4 | N5: The study area is mentioned as Korean waters, but how to decide marine borders? | O5: Reviews in fish biology and fisheries | P5: 2014 | Q5: Jung, S; Pang, IC; Lee, JH; Choi, I; Cha, HK | R5: 10.1007/s11160-013-9310-1
B6: E22 | C6: =LEFT(B6,1) & TEXT(RIGHT(B6,LEN(B6)-1),"0000") -> E0022 | D6: E0022 | E6: alpine | F6: North by north-west: climate change and directions of density shifts in birds | G6: There is increasing evidence that climate change shifts species distributions towards poles and mountain tops. However, most studies are based on presence-absence data, and either abundance or the observation effort has rarely been measured. In addition, hardly any studies have investigated the direction of shifts and factors affecting them. Here, we show using count data on a 1000km south-north gradient in Finland, that between 1970-1989 and 2000-2012, 128 bird species shifted their densities, on average, 37km towards the north north-east. The species-specific directions of the shifts in density were significantly explained by migration behaviour and habitat type. Although the temperatures have also moved on average towards the north north-east (186km), the species-specific directions of the shifts in density and temperature did not correlate due to high variation in density shifts. Findings highlight that climate change is unlikely the only driver of the direction of species density shifts, but species-specific characteristics and human land-use practices are also influencing the direction. Furthermore, the alarming results show that former climatic conditions in the north-west corner of Finland have already moved out of the country. This highlights the need for an international approach in research and conservation actions to mitigate the impacts of climate change. | H6: maybe | I6: Sakiyama | J6: No | N6: The study is conducted in Finland. | O6: Global change biology | P6: 2016 | Q6: Lehikoinen, A; Virkkala, R | R6: 10.1111/gcb.13150
B7: E29 | C7: =LEFT(B7,1) & TEXT(RIGHT(B7,LEN(B7)-1),"0000") -> E0029 | D7: E0029 | E7: alpine | F7: Seasonal dry-down rates and high stress tolerance promote bamboo invasion above and below treeline | G7: How species invasions impact ecosystem structure and function at important ecotones or boundaries is unknown, but may provide insight into the impacts of climate change and the mechanisms underlying community change. The dwarf bamboo, Sasa kurilensis, may be a good system to understand these issues, as the species impacts ecosystem features as it encroaches beyond treeline into alpine systems. We used remote sensing imagery spanning a 35 year period to quantify S. kurilensis expansion patterns across its range, measured growth and stress tolerances of S. kurilensis above and below treeline, and evaluated components of growth to reveal how shifts in light and water limitations influence the ontogeny of height, branching, and leaf production. We show that S. kurilensis more than doubled its abundance across its range, but more than tripled its abundance near and above treeline. Soil dry-down rates were a key driver of invasion above and below treeline, where growth rates decreased with more rapid rates of soil moisture dry-down. We found S. kurilensis responds to competition and climate stress by increasing allocation to belowground structures at high elevations. Further, it invests more carbon in fewer-yet taller and heavier-aboveground structures in low-light, low elevation environments. It appears this species' success is driven by considerable morphological and physiological flexibility, coupled with changes in water balance associated with snowmelt that in each habitat results in sites increasingly hospitable to bamboo. Overall, this study links resource allocation strategies and physiological responses to climate change and provides a mechanistic explanation of invasion success. | H7: maybe | I7: Sakiyama | J7: Maybe | K7: Alpine | L7: Yes | M7: Table 1 | N7: Computing abundance weighted range shift is possible with the data. | O7: Plant ecology | P7: 2016 | Q7: Winkler, DE; Amagai, Y; Huxman, TE; Kaneko, M; Kudo, G | R7: 10.1007/s11258-016-0649-y
B8: E30 | C8: =LEFT(B8,1) & TEXT(RIGHT(B8,LEN(B8)-1),"0000") -> E0030 | D8: E0030 | E8: alpine | F8: Two types of strong local wind captured by simultaneous multiple-site radiosonde soundings across a mountain range | G8: A radiosonde observation method is presented, consisting of simultaneous radiosonde observations at closely spaced multiple sites using balloons with varied buoyancies. This method was employed during a strong wind event (Suzuka-oroshi) on the lee side of the Suzuka mountain range, Japan, to derive the detailed structure of the wind as it crossed the mountains. Batches of six radiosondes were launched simultaneously from a line of four sites, using balloons with three different degrees of buoyancy. The four sites were 13 km apart along a 35-km-long transect roughly aligned with the prevailing wind. The observations documented two flow regimes: a downslope flow perpendicular to the mountain range, similar to a windstorm, and an unexpectedly strong low-level jet flowing parallel to the mountain range. The method was more successful at delineating the first regime than the second. The first regime was well simulated by a numerical experiment, but the second regime was not. The vertical wind associated with the downslope windstorm was inferred from the changing slopes of potential temperature isentropes. Comparison of the balloon ascent rates with these isentropes meanders and the simulated vertical wind showed that fluctuations in balloon ascent rate provide reliable information on the vertical direction of the wind. An analysis of the second regime using a long-term meteorological dataset shows that the onset of the low-level jet is related to the synoptic-scale shift in vorticity from positive to negative in the observation area. This vorticity shift appears to be a useful indicator for the low-level jet regime. | H8: yes | I8: Sakiyama | J8: No | N8: The study is about wind. | O8: Monthly weather review | P8: 2016 | Q8: Komatsu, KK; Tachibana, Y | R8: 10.1175/MWR-D-15-0347.1
B9: E31 | C9: =LEFT(B9,1) & TEXT(RIGHT(B9,LEN(B9)-1),"0000") -> E0031 | D9: E0031 | E9: alpine | F9: Post-glacial east asian origin of the alpine shrub phyllodoce aleutica (ericaceae) in beringia | G9: Aim: The ice-free area around the Bering Land Bridge, Beringia, has been noted as an important refugium of organisms preferring cold environments such as arctic-alpine plants throughout the Pleistocene climate oscillations. Although numerous phylogeographical studies have supported this refugium, recent studies have challenged the idea of a homogeneous refugium in Beringia. We aim to examine a novel scenario of the post-glacial colonization history of an alpine plant Phyllodoce aleutica in Beringia. Location: The Japanese Archipelago, the Kamchatka Peninsula, the Aleutian Islands, Alaska. Method: The range-wide genetic structure of P. aleutica was elucidated by sequencing 13 nuclear loci. The phylogeographical history was inferred using model-based approaches based on coalescent simulations together with the potential distributions predicted by ecological niche modelling. Results: Bayesian clustering and phylogenetic networks revealed that P. aleutica was divided into three geographically structured groups: the main island of the Japanese Archipelago, the northern island of the archipelago (Hokkaido) and Beringia, including eastern Hokkaido. The demographic history underlying the genetic structure and the potential distributions at present and during Last Glacial Maximum suggest that their divergence likely predated the last glacial period. Except for genetic admixture with the sister species Phyllodoce glanduliflora, populations in Alaska exhibited lower genetic diversity than those in East Asia and exclusively shared two widespread genotypes. Approximate Bayesian computation showed that a demographic model postulating post-glacial expansion into Alaska fit better than alternative models. Main conclusions: Our study suggests that P. aleutica in eastern Beringia originated through post-glacial colonization from East Asia, providing novel insight into the biogeographical history of alpine flora in Beringia. | H9: yes | I9: Sakiyama | J9: No | N9: The study is about phylogeography of alpine plants. | O9: Journal of biogeography | P9: 2018 | Q9: Ikeda, H; Yakubov, V; Barkalov, V; Setoguchi, H | R9: 10.1111/jbi.13230
B10: E33 | C10: =LEFT(B10,1) & TEXT(RIGHT(B10,LEN(B10)-1),"0000") -> E0033 | D10: E0033 | E10: alpine | F10: Elevation-related climate trends dominate fungal co-occurrence network structure and the abundance of keystone taxa on mt. Norikura, japan | G10: Soil fungi play an important role in promoting nutrient cycling and maintaining ecosystem stability. Yet, there has been little understanding of how fungal co-occurrence networks differ along elevational climate gradients, a topic of interest to both macroecology and climate change studies. Based on high-throughput sequencing technology, we investigated the trend in co-occurrence network structure of soil fungal communities at 11 elevation levels along a 2300 m elevation gradient on Mt. Norikura, Japan, and identified the keystone taxa in the network, hypothesizing a progressive decline in network connectivity with elevation due to decreased plant diversity and enhanced environmental stress caused by changes in climate and soil characteristics. Our results demonstrated that network-level topological features such as network size, average degree, clustering coefficient, and modularity decreased significantly with increasing elevation, indicating that the fungal OTUs at low elevation were more closely associated and the network structure was more compact at low elevations. This conclusion was verified by the negative correlation between positive cohesion, negative cohesion and elevation. Moreover, the negative/positive cohesion ratio reached its peak value in mid-elevations with moderate environmental stress, indicating that the fungal community structure in mid-elevations was more stable than that at other elevations. We also found that the keystone taxa were more abundant at lower elevations. Furthermore, statistical analysis revealed that against a background of uniform geology, climate may play a dominant role in determining the properties and intensity of soil fungal networks, and significantly affect the abundance distribution of keystone taxa. These findings enhance understanding of the pattern and mechanism of the fungal community co occurrence network along elevation, as well as the responses of microorganisms to climate change on a vertical scale in montane ecosystems. Importance: Exploration of the elevational distribution of microbial networks and their driving factors and mechanisms may provide opportunities for predicting potential impacts of environmental changes, on ecosystem functions and biogeographic patterns at a broad scale. Although many studies have explored patterns of fungal community diversity and composition along various environmental gradients, it is unclear how the topological structure of co-occurrence networks shifts along elevational temperature gradients. In this study, we found that the connectivity of the fungal community decreased with increasing elevation and that climate was the dominant factor regulating co-occurrence patterns, apparently acting indirectly through soil characteristics. Our results also suggest that higher elevations on mountains have fewer keystone taxa than low elevations. These patterns may be related to the decrease of plant diversity and the increase of environmental stress along elevation gradients. (c) 2021 Elsevier B.V. All rights reserved. | H10: maybe | I10: Sakiyama | J10: No | N10: The study is about fungi network structure. | O10: Science of the total environment | P10: 2021 | Q10: Yang, Y; Shi, Y; Kerfahi, D; Ogwu, MC; Wang, JJ; Dong, K; Takahashi, K; Moroenyane, I; Adams, JM | R10: 10.1016/j.scitotenv.2021.149368
B11: E35 | C11: =LEFT(B11,1) & TEXT(RIGHT(B11,LEN(B11)-1),"0000") -> E0035 | D11: E0035 | E11: alpine | F11: Studies on glacial landforms in japan between 1960 and 2010: personal review | G11: Fifty years of studies on glacial landforms in Japan between 1960 and 2010 are reviewed from the personal perspective of a researcher who devoted a major part of his life to these stu dies. The 1960s was a period in which there was a paradigm shift in the history of glacial landform studies in Japan. This resulted from a series of studies by Tomoya Iozawa using aerial photograph interpretation. He was the first researcher to observe and identify all of the glacial landforms in Japan using aerial photographs, and divided them into two groups: the older and more widespread (Yokoo Stage) and the younger and much less widespread (Karasawa Stage). Following his methodology and staging, extensive research was done in the 1970s, and tephrochronological studies revealed that the older and younger stages correspond to MIS 4 and 2 respectively, although MIS 3 glaciation was recognized later in the Hidaka Range, Hokkaido. A researchers union of glacial and periglacial landforms called Kanrei-chikei Danwakai was established in 1972, Proposed and organized by Isozawa and other young students including the author, it stimulated research. In the 1980s, a reconstruction of the mass balance and flows of past glaciers from glacial landforms was attempted by the author and other researchers. This led to the estimation of the Equilibrium Line Altitude (ELA) of former glaciers in Japan. Inventory work and monitoring of perennial snow patches in the Japanese Alps were also begun in the 1980s, and they encouraged studies on the transformation from perennial snow patch to glacier. In addition, the discovery of an ice body at the bottom of Kuranosuke Cirque, Mt. Tateyama, Northern Japanese Alps gave an important hint to estimating the present (topographical) snowline altitude, which could be much lower than the former evaluation determined only from free air temperature. Both the study of perennial snow patches and mapping of the former ELA clarified the importance of precipitation when determining snowline altitude, and the present ELA was estimated at 2970 m just below the peak of Mt. Tateyama (3003 m). Since the 1990s, glacial landform studies became more closely related to global climatic change within the framework of IGBP-PAGES. Glacial fluctuations in Japan in the last glacial period were mainly controlled by monsoon changes and migration of westerlies, which caused a southern migration of the polar frontal zone. Although the glaciers in Japan were small, even in the glacial period, it is now believed that they are an important indicator of climatic changes because they are very sensitive to monsoon and westerly changes. | H11: yes | I11: Sakiyama | J11: No | N11: The study is a review on glacial landforms in Japann\. | O11: Journal of geography-chigaku zasshi | P11: 2012 | Q11: Ono, Y | R11: 10.5026/jgeography.121.187
B12: E36 | C12: =LEFT(B12,1) & TEXT(RIGHT(B12,LEN(B12)-1),"0000") -> E0036 | D12: E0036 | E12: alpine | F12: Genomic shifts, phenotypic clines, and fitness costs associated with cold tolerance in the asian tiger mosquito | G12: Climatic variation is a key driver of genetic differentiation and phenotypic traits evolution, and local adaptation to temperature is expected in widespread species. We investigated phenotypic and genomic changes in the native range of the Asian tiger mosquito, Aedes albopictus. We first refine the phylogeographic structure based on genome-wide regions (1,901 double-digest restriction-site associated DNA single nucleotide polymophisms [ddRAD SNPs]) from 41 populations. We then explore the patterns of cold adaptation using phenotypic traits measured in common garden (wing size and cold tolerance) and genotype-temperature associations at targeted candidate regions (51,706 exon-capture SNPs) from nine populations. We confirm the existence of three evolutionary lineages including clades A (Malaysia, Thailand, Cambodia, and Laos), B (China and Okinawa), and C (South Korea and Japan). We identified temperature-associated differentiation in 15 out of 221 candidate regions but none in ddRAD regions, supporting the role of directional selection in detected genes. These include genes involved in lipid metabolism and a circadian clock gene. Most outlier SNPs are differently fixed between clades A and C, whereas clade B has an intermediate pattern. Females are larger at higher latitude yet produce no more eggs, which might favor the storage of energetic reserves in colder climate. Nondiapausing eggs from temperate populations survive better to cold exposure than those from tropical populations, suggesting they are protected from freezing damages but this cold tolerance has a fitness cost in terms of egg viability. Altogether, our results provide strong evidence for the thermal adaptation of A. albopictus across its wide temperature range. | H12: yes | I12: Sakiyama | J12: No | N12: This is a genetic study. | O12: Molecular biology and evolution | P12: 2022 | Q12: Sherpa, S; Tutagata, J; Gaude, T; Laporte, F; Kasai, S; Ishak, IH; Guo, X; Shin, J; Boyer, S; Marcombe, S; Chareonviriyaphap, T; David, JP; Chen, XG; Zhou, XH; Després, L | R12: 10.1093/molbev/msac104
B13: E39 | C13: =LEFT(B13,1) & TEXT(RIGHT(B13,LEN(B13)-1),"0000") -> E0039 | D13: E0039 | E13: alpine | F13: Molecular phylogeny, biogeography and ecological niche modelling of cardiocrinum (liliaceae): insights into the evolutionary history of endemic genera distributed across the sino-japanese floristic region | G13: Background and Aims The patterns of evolutionary assembly in the Sino-Japanese floristic region (SJFR) remain largely unknown due to a lack of integrative multidimensional studies throughout the region. To address this issue, we elucidated the evolutionary history of Cardiocrinum (Liliaceae), a genus containing four taxa distributed across the SJFR. Methods Fifty-four populations were sampled throughout the geographical range of Cardiocrinum to assess gen-etic structure, analyse phylogenetic relationships and reconstruct ancestral area based on six chloroplast DNA (cpDNA) fragments and three low copy nuclear genes (LCNG). Ecological niche modelling was used to examine the potential range shifts of Cardiocrinum in response to climatic change. Key Results The molecular data showed high genetic similarity in the cpDNA (98.37 %) and LCNG (94.53 %) sequences. The biogeographical analyses revealed that the ancestor of Cardiocrinum diversified during the late Miocene (approx. 7.32 Mya) in Central China. The ancestor of the C. giganteum lineage dispersed westward to the Himalayas and south-west China with the split between C. giganteum and C. giganteum var. yunnanense occurring around 4.11 Mya consistent with the period of orogeny of the Hengduan Mountains. Some populations of the C. cathayanum lineage dispersed eastward to south Japan via the land bridge approx. 4.97 Mya, providing opportu-nities for allopatric speciation of C. cordatum. The predicted suitable habitats of Cardiocrinum have become smaller and more fragmented since the Last Glacial Maximum. Conclusions Our study provides evidence of a biogeographical pattern of dispersal from Central China to the Himalayas in the west and Japan in the east for genera distributed across the SJFR, and highlights that the orogeny of the Hengduan Mountains and fluctuations of the sea level of the East China Sea played important roles in pro-moting species divergence. | H13: yes | I13: Sakiyama | J13: No | N13: This is a genetic study. | O13: Annals of botany | P13: 2017 | Q13: Yang, LQ; Hu, HY; Xie, C; Lai, SP; Yang, M; He, XJ; Zhou, SD | R13: 10.1093/aob/mcw210
B14: E45 | C14: =LEFT(B14,1) & TEXT(RIGHT(B14,LEN(B14)-1),"0000") -> E0045 | D14: E0045 | E14: alpine | F14: Climate change-based models predict range shifts in the distribution of the only asian plethodontid salamander: karsenia koreana | G14: AbstractPopulations see their range fluctuate in relation to environmental variations, including climate change, and their survival is linked to the maintenance of large enough populations and broad enough distributions during these variations. Most amphibian populations are threatened by numerous ecological and anthropogenic variables acting in synergy with climate change. Accumulating basic ecological data such as range enables the development of population and range dynamics, themselves resulting on adequate conservation plans.Karsenia koreanais the only known Asian plethodontic salamander, occurring in a very restricted area only. Based on presence data, we created an ecological model using six bioclimatic factors with low multicollinearity to define the adequate habitat of the species, and we modelled the predicted suitability of the Korean landscape following four Representative Concentration Pathways (RCPs) predicting climate change scenarios based on CO2concentrations in 2050 and 2070. The maximum entropy model for the current distribution produced a landscape suitability considerably wider than the current known distribution. The projected ranges for each RCP indicated marked increases, decreases and shifts in areas with suitable landscapes due to climate change. The lowest RCP prediction resulted in an increase in suitable area, although potentially without connectivity with current populations, while the highest RCP predictions resulted in a decrease. Our results highlight the potential negative impact of climate change, thus requiring updates in conservation plans forK. koreana. The methods used here can be replicated with any land-dwelling species, and our results reflect expected range shifts for most amphibians of the northern hemisphere. | H14: maybe | I14: Sakiyama | J14: No | N14: This study examines the future range shift. | O14: Scientific reports | P14: 2019 | Q14: A Borzée, D Andersen, J Groffen, HT Kim, Y Bae… | R14: 10.1038/s41598-019-48310-1
B15: E46 | C15: =LEFT(B15,1) & TEXT(RIGHT(B15,LEN(B15)-1),"0000") -> E0046 | D15: E0046 | E15: alpine | F15: Distinct phylogeographic structure of the halophyte Suaeda malacosperma (Chenopodiaceae/Amaranthaceae), endemic to Korea–Japan region, influenced by historical range shift dynamics | G15: Wide-ranging changes to the coastline of East Asia during the glacial periods of the Quaternary might have significantly influenced the genetic structure of coastal plants. To verify its historical migration and potential breaks to gene flow, we investigated the genetic structure of the vulnerable halophyte Suaeda malacosperma, whose distribution is restricted to brackish tidal areas of Korea and Japan. Two chloroplast DNA (cpDNA) regions (rpl32-trnL, trnH-psbA) were used for five individuals each from 11 populations. SNP data obtained via multiplexed ISSR genotyping by sequencing (MIG-Seq) were used for 181 individuals from those populations. Ecological niche modeling (ENM) was combined with genetic analyses to compare current and past distributions. The cpDNA sequences and MIG-Seq data revealed largely congruent results indicating that S. malacosperma consists of three genetic clusters: western coast of Korea, southern coast of Korea, and Japan. The patterns produced through structure analysis and cpDNA haplotypes showed that the gene flow occurred at or after the last glaciation from Japan to the southern coast of Korea via the Korea/Tsushima Strait land bridge. Despite the coastal habitat of this species, ocean currents had less influence. Integrating genetic data with past distribution models by ENM provided insight into potential recolonization routes from refugia in each region. Those data suggested that, instead of contemporary gene flow, a historical range shift due to climate change affected the population structure. These results support the need for a conservation strategy and advance our understanding about the historical range dynamics of coastal plants in temperate East Asia. | H15: yes | I15: Sakiyama | J15: No | N15: This is a genetic study. | O15: Plant Systematics and Evolution | P15: 2019 | Q15: JS Park, K Takayama, Y Suyama, BH Choi | R15: 10.1007/s00606-018-1562-8
B16: E52 | C16: =LEFT(B16,1) & TEXT(RIGHT(B16,LEN(B16)-1),"0000") -> E0052 | D16: E0052 | E16: alpine | F16: Seasonal changes in the ratio of congeneric charrs in northern japanese tributaries with different temperature regimes | G16: Background: The species distributions and community compositions of stream shes are often shaped by water temperature. Stream salmonids, for example, show longitudinal gradients or marked community differences between spring-fed vs. non-spring-fed streams, which may be a result of species-speci c temperature preferences, interspeci c competition, or their interaction (i.e., temperature-dependent competition). Despite the widely reported patterns, how such temperature-associated distributions change across seasons remains largely unknown. If temperature is the main driver, the pattern will change across seasons. Alternatively, seasonal patterns will be obscured if other factors, such as species speci c life histories or seasonal aggregation, are important. Here, we investigated the effects of water temperature on the abundance and species ratio of two potentially competing salmonids, southern Asian Dolly Varden Salvelinus curilus and white-spotted charr Salvelinus leucomaenis, in 6 small tributaries with different temperature regimes (i.e., spring-fed and non-spring-fed) across seasons. Results: Across seasons, the southern Asian Dolly Varden dominated in spring-fed tributaries, whereas white-spotted charr dominated in non-spring-fed tributaries. The seasonal variation in the abundance of southern Asian Dolly Varden and species ratio were explained by water temperature uctuation, whereas that of white-spotted charr was not explained by the temperature uctuation. No winter aggregation was observed in any of the tributaries. In addition, only the species ratio in summer was explained by the water temperature, and the water temperature did not fully explain the species ratio. Conclusions: Our results indicated that temperature preference and/or the strength of interspeci c competition may differ across seasons, which is expected to determine the seasonal distribution patterns in spring-fed and non-spring-fed tributaries. This study underscores the importance of considering seasons when evaluating temperature effects on the distribution of stream salmonids. | H16: yes | I16: Sakiyama | J16: No | N16: This study is about fish community ecology. | O16: Preprint | P16: 2023 | Q16: T Yamada, I Koizumi, F Nakamura | R16: 10.21203/rs.3.rs-2465444/v1 | S16: none found
B17: E70 | C17: =LEFT(B17,1) & TEXT(RIGHT(B17,LEN(B17)-1),"0000") -> E0070 | D17: E0070 | E17: alpine | F17: Aquatic species shows asymmetric distribution range shifts in native and non-native areas | G17: IntroductionClimate change is reshaping the geographical distribution of species across the globe. In marine ecosystems, climate change creates novel challenges to an environment impacted by numerous anthropogenic stressors. Forecasting shifts in species distribution, including the expansion of non-indigenous species under climate change scenarios, is a management challenge for today’s world.MethodsWe applied Bayesian Additive Regression Tree (BART) models to investigate the environmental factors modulating the occurrence and habitat preferences of the Atlantic blue crab Callinectes sapidus Rathbun, 1896 in native and non-native areas. With BART models, we also aimed to predict its current and future distributions under two climate change scenarios (RCPs 4.5 and 8.5). BART models were performed using global occurrences of the Atlantic blue crab – recorded from 1830 to 2022 – and several environmental covariates (i.e., water temperature, salinity, current velocity, and rugosity). Model accuracy was assessed with the Area Under the Curve (AUC) and True Skill Statistics (TSS) criteria. Cross-validation experiments were made to balance accuracy prediction and uncertainty model prediction intervals.Results and discussionAUC and TSS values indicated that data validation was successful for the BART model. Water temperature was the most critical variable affecting the presence probability of the Atlantic blue crab. The BART model predicts asymmetric distribution range shifts on both sides of the Atlantic Ocean. The non-native populations will experience broader shifts in their distribution range than in the native range, and the RCP 8.5 scenario model outputs predict a wider distribution range by the end of the century. Overall, we anticipate significant ecological changes in native and non-native areas. The range expansion in native areas is often equivalent to the ecological shifts induced by invasive species, so lessons learned by ecologists and managers in non-native areas will provide actionable insights to managers in native areas. | H17: maybe | I17: Sakiyama | J17: No | N17: This study examines the future range shift. | O17: Frontiers in Marine Science | P17: 2023 | Q17: EFS Costa, J Encarnação, MA Teodósio… | R17: 10.3389/fmars.2023.1158206
B18: E76 | C18: =LEFT(B18,1) & TEXT(RIGHT(B18,LEN(B18)-1),"0000") -> E0076 | D18: E0076 | E18: alpine | F18: Deep phylogeographic breaks in magpie pica pica across the holarctic: concordance with bioacoustics and phenotypes | G18: We examined sequences of the mitochondrial control region in magpies (Pica pica) from the entire distribution range and found deep genetic splits into four major lineages: (1) group West (Europe-Siberia), (2) group East (southern Far East), (3) P. p. mauritanica (North Africa), and (4) P. p. hudsonia (North America). These lineages show a geographic pattern corresponding to known subspecies or subspecies groups. Genetic variation within the widely-distributed group West is low and neutrality tests supported a recent expansion scenario. The haplotypes from Kamchatka, representing a separated sublineage with clear affinity to the European-Siberian group, are almost identical, implying a recent bottleneck. Group East contained two subclades without clear geographic pattern, presumably due to admixing of populations that had diverged in Pleistocene refuges. The homogeneity of the Kyushu population supports historical reports of introduction of the species from Korea. In contrast, the high variation in the recently established Hokkaido population may reflect an ongoing invasion from several populations of the Far Eastern mainland. Bioacoustic data based on chatter call differentiate groups of subspecies and reflect phylogeographic patterns, i.e., mitochondrial lineages. Furthermore, we report the fast spreading of P. p. jankowskii towards the west along the upper Amur River, and a slower shifting of P. p. leucoptera in the opposite direction thus yielding a new contact zone. Overall, our data support a scenario of divergence in geographic isolation, but the ongoing expansion of distribution ranges may lead to major changes in phylogeographic patterns. | H18: yes | I18: Hayashi | J18: No | N18: The study did not evaluate range shift. | O18: Zoological science | P18: 2017 | Q18: AP Kryukov, LN Spiridonova, S Mori, VY Arkhipov… | R18: 10.2108/zs160119
B19: E131 | C19: =LEFT(B19,1) & TEXT(RIGHT(B19,LEN(B19)-1),"0000") -> E0131 | D19: E0131 | E19: alpine | F19: Assessing non-native invasive orthoptera in europe | G19: Orthoptera encompasses 29,000 species. Due to their ability to migrate long-distances through hitchhiking or active dispersal but also due to their wide dietary spectrum, several orthoptera species can pose a phytosanitary threat. Despite information being scarce and contrasting among sources, we compiled literature on non-native Orthoptera species in Europe for this scoping review. We identified 41 relevant species, 35 are non-native (non-native to Europe n = 8, partly native to Europe n = 21, native range unknown/no information available n = 6), two arguably invasive species to Europe due to proven impacts, two are questionable and another two cryptogenic. Of these, 23 species are considered established. The two invasive orthopterans were the Moroccan LocustDociostaurus maroccanusand the Desert LocustSchistocerca gregaria, which are invasive in several European countries. Non-native orthopterans can react very positively to climate warming, resulting in expanding geographical distributions. Furthermore, the number of invasive orthopterans in Europe is likely higher due to a paucity of assessments, increasing introduction rates, and observable impacts on agriculture as well as native species. While e.g., the Migratory LocustLocusta migratoriacauses large-scale damage to crops by forming swarms, the southern oak bush cricketMeconema meridionalehas a negative impact on native species, but neither species is listed as invasive. Besides this, there are other non-native Orthoptera species that could become invasive given increasing reproduction rates due to suitable conditions. Globalization and rising temperatures due to global warming are both increasing introduction rates and concomitantly the availability of suitable locations for reproduction, successful establishments, and finally swarm building. This will increase the probability of damages to agriculture, thus the economy and native biodiversity, eventually endangering human well-being. It is therefore important to monitor and study the invasiveness and impacts of non-native Orthoptera species to develop efficient management or preventive mitigation strategies. | H19: maybe | I19: Hayashi | J19: No | N19: The study is conducted in Europe. | O19: Preprint | P19: 2023 | Q19: AK Kulessa, A Kouba, D Renault, I Soto… | R19: 10.21203/rs.3.rs-2828952/v1 | S19: none found
B20: E136 | C20: =LEFT(B20,1) & TEXT(RIGHT(B20,LEN(B20)-1),"0000") -> E0136 | D20: E0136 | E20: alpine | F20: Conservation biogeography: our place in the world | G20: Conservation biogeography was imagined as a distinct "applied and interdisciplinary science concerned with the conservation of nature" less than two decades ago. This chapter reviews the development of conservation biogeography since its inception a little over one and half decades ago. It aims to, first, provide a brief timeline of progress in the development of this subdiscipline, followed by an overview of the claimed and examined purview of the field. The chapter then briefly examines several highlights emanating from this approach to date, and concludes with a few speculations on how the subdiscipline might continue to develop in productive directions. Conservation biogeography appears to have made progress since 2005 in its attempt to delineate, conceptually and empirically, a portion of the spatial scale within the vast realm of conservation biology that has not always been of a focal concern among biodiversity researchers. | H20: maybe | I20: Hayashi | J20: No | N20: The study did not evaluate range shift. | O20: Biogeography: an integrative approach of the … | P20: 2021 | Q20: BR Riddle | R20: 10.1002/9781119882381.ch13
B21: E153 | C21: =LEFT(B21,1) & TEXT(RIGHT(B21,LEN(B21)-1),"0000") -> E0153 | D21: E0153 | E21: alpine | F21: Priority coral conservation areas under global warming in the amami islands, southern japan | G21: Coral reef ecosystems are highly sensitive to climate change. The Amami Islands in Southern Japan were selected as the study area. It is important to select areas that should be given priority for conservation and subsequently direct resources there. The objective of this study was to identify locations with low bleaching potential against future increases in water temperature, as well as high larval recruitment from other areas and high larval supply capacity to other areas based on connectivity. We simulated the coral bleaching rate and larval connectivity under historical (2000s) and future (RCP2.6 and RCP8.5 in the 2090s) climate conditions using a high-resolution (1/30° × 1/50°) future ocean regional projection dataset. From the model simulation, coral bleaching did not occur in most areas in the 2000s. However, the bleaching frequency would increase significantly under RCP8.5 in the 2090s, and it is projected that mass coral bleaching events will occur in more than half of the years of that decade. Larval dispersion simulation shows that some particles released from the Amami Islands remain in the same area. However, fluctuations in both the sink strength and the source strength among the islands were larger than those within each island, and differences in connectivity between scenarios were not apparent. Grid cells that have a low bleaching rate and high potential for a larval sink and source under each scenario were selected. Since our results can identify priority conservation areas, it is important to conduct conservation and/or adaptation strategies according to the specific characteristics of each island. | H21: yes | I21: Hayashi | J21: No | K21: Marine | N21: The study did not evaluate range shift. | O21: Coral reefs | P21: 2022 | Q21: H Abe, NH Kumagai, H Yamano | R21: 10.1007/s00338-022-02309-9
B22: E156 | C22: =LEFT(B22,1) & TEXT(RIGHT(B22,LEN(B22)-1),"0000") -> E0156 | D22: E0156 | E22: alpine | F22: Assessing the speciation of a cold water species, japanese sand lance ammodytes personatus, in the northwestern pacific by aflp markers | G22: The use of molecular techniques in biodiversity research increasingly results in the recognition of multiple divergent mitochondrial DNA (mtDNA) lineages below the morphospecies level. However, the overlapping distribution of multiple divergent lineages raises the question of whether some of these lineages are in fact cryptic species. Assessing the status of these divergent lineages, delimiting evolutionarily significant units (ESUs), and identifying the dominant evolutionary and ecological drivers are critical components of successful wildlife conservation and management strategies. Amplified fragment length polymorphism (AFLP) markers were applied to characterize the phylogeography pattern of a cold water species, the Japanese sand lance Ammodytes personatus, in warm and cold ocean currents. A total of 211 individuals sampled from 12 populations through the species’ range, including samples from Kuroshio Current, Oyashio Current, Tsushima Current, and Yellow Sea, were analyzed. The Bayesian assignment probability test and Neighbor joining (NJ) analysis divided these populations into two genetically and geographically distinct clades (northern and southern clades) characterized by different sea surface temperatures. The incongruence between nuclear clades and previous mitochondrial lineages suggested that A. personatus is indeed composed of at least two genetically divergent cryptic species. Pleistocene glaciation isolation after secondary contact, local thermal adaptation, and isolation by distance may explain the observed geographic pattern of two cryptic species and genetic structure within clades. | H22: yes | I22: Hayashi | J22: No | K22: Marine | N22: The study did not evaluate range shift. | O22: Animals | P22: 2018 | Q22: Z Han, Z Wang, T Gao, T Yanagimoto, K Iida | R22: 10.3390/ani8120224
B23: E160 | C23: =LEFT(B23,1) & TEXT(RIGHT(B23,LEN(B23)-1),"0000") -> E0160 | D23: E0160 | E23: alpine | F23: Adaptation to climate change through genetic accommodation and assimilation of plastic phenotypes | G23: Theory suggests that evolutionary changes in phenotypic plasticity could either hinder or facilitate evolutionary rescue in a changing climate. Nevertheless, the actual role of evolving plasticity in the responses of natural populations to climate change remains unresolved. Direct observations of evolutionary change in nature are rare, making it difficult to assess the relative contributions of changes in trait means versus changes in plasticity to climate change responses. To address this gap, this review explores several proxies that can be used to understand evolving plasticity in the context of climate change, including space for time substitutions, experimental evolution and tests for genomic divergence at environmentally responsive loci. Comparisons among populations indicate a prominent role for divergence in environmentally responsive traits in local adaptation to climatic gradients. Moreover, genomic comparisons among such populations have identified pervasive divergence in the regulatory regions of environmentally responsive loci. Taken together, these lines of evidence suggest that divergence in plasticity plays a prominent role in adaptation to climatic gradients over space, indicating that evolving plasticity is also likely to play a key role in adaptive responses to climate change through time. This suggests that genetic variation in plastic responses to the environment (G × E) might be an important predictor of species' vulnerabilities to climate-driven decline or extinction.This article is part of the theme issue ‘The role of plasticity in phenotypic adaptation to rapid environmental change’. | H23: maybe | I23: Hayashi | J23: No | N23: The study did not evaluate range shift. | O23: Philosophical Transactions of the Royal Society B | P23: 2019 | Q23: M Kelly | R23: 10.1098/rstb.2018.0176
B24: E166 | C24: =LEFT(B24,1) & TEXT(RIGHT(B24,LEN(B24)-1),"0000") -> E0166 | D24: E0166 | E24: alpine | F24: Species response to contemporary climate change | G24: Species distribution modelling comprises a range of widely used tools for predicting potential changes in insect pest species distributions with climate change. We review the current literature to see the effectiveness of different approaches, particularly in comparing predictions based on current distribution data (correlative or 'environmental niche models') and those based on life-history traits and determination of thermal limits (mechanistic models). We review new developments in implementing processes such as dispersal and biotic interactions within species distribution models and how these could be used to develop management strategies incorporating natural enemies into climate change predictions. We propose that species distribution models should be linked with key trait data where possible to inform better of response to climate change. | H24: maybe | I24: Hayashi | J24: No | N24: The study did not evaluate range shift. | O24: The SAGE Handbook of Biogeography | P24: 2011 | Q24: TH Sparks, A Menzel, J Peñuelas… | R24: N/A
B25: E169 | C25: =LEFT(B25,1) & TEXT(RIGHT(B25,LEN(B25)-1),"0000") -> E0169 | D25: E0169 | E25: alpine | F25: “Land Emergence” and “Elevation Shift” Affect Diversification: A New Perspective Toward Understanding the High Species Diversity of Terrestrial Animals in Japan | G25: Animal species in Japan are characterized by a high degree of endemism. Recent phylogeographic studies have revealed interesting and unexpected patterns of diversification in the islands adjacent to the main Japanese islands (Hokkaido, Honshu, Shikoku, and Kyushu) and the within-island diversification in the main islands. In this chapter, I propose two potential models to explain such diversification: 'land emergence' effects and 'elevation shift' effects, based on changes in animal distribution in response to climate or habitat alteration during the repeated glaciation and post-glaciation periods in the Pleistocene era. In the land emergence effect, population expansion and contraction in response to land emergence and disappearance contributed to the dynamic changes in morphological and genetic characters in the four main islands and their adjacent offshore islands. In the elevation shift effect, 'cryptic barriers' and 'cryptic corridors' were formed through elevation shifts in response to climatic changes in the past. The effect also contributed to the formation of diversification patterns among the low elevation species. For further understanding of diversification of Japanese animals, both land emergence and elevation shift effects should be evaluated for each species, with careful consideration of the 'connectivity' of animal dispersal. | H25: yes | I25: Hayashi | J25: No | N25: The study discuss species distribution during the glacial period. | O25: Species diversity of animals in japan | P25: 2016 | Q25: M Motokawa | R25: 10.1007/978-4-431-56432-4_1
B26: E177 | C26: =LEFT(B26,1) & TEXT(RIGHT(B26,LEN(B26)-1),"0000") -> E0177 | D26: E0177 | E26: alpine | F26: Poleward shifts in geographical ranges of butterfly species associated with regional warming | G26: Mean global temperatures have risen this century, and further warming is predicted to continue for the next 50–100 years1,2,3. Some migratory species can respond rapidly to yearly climate variation by altering the timing or destination of migration4, but most wildlife is sedentary and so is incapable of such a rapid response. For these species, responses to the warming trend should be slower, reflected in poleward shifts of the range. Such changes in distribution would occur at the level of the population, stemming not from changes in the pattern of individuals' movements, but from changes in the ratios of extinctions to colonizations at the northern and southern boundaries of the range. A northward range shift therefore occurs when there is net extinction at the southern boundary or net colonization at the northern boundary. However, previous evidence has been limited to a single species5 or to only a portion of the species' range6,7. Here we provide the first large-scale evidence of poleward shifts in entire species' ranges. In a sample of 35 non-migratory European butterflies, 63% have ranges that have shifted to the north by 35–240 km during this century, and only 3% have shifted to the south. | H26: maybe | I26: Hayashi | J26: No | N26: The study is conducted in Northern Europe. | O26: Nature | P26: 1999 | Q26: C Parmesan, N Ryrholm, C Stefanescu, JK Hill… | R26: 10.1038/21181
B27: E182 | C27: =LEFT(B27,1) & TEXT(RIGHT(B27,LEN(B27)-1),"0000") -> E0182 | D27: E0182 | E27: alpine | F27: How does climate warming affect plant‐pollinator interactions? | G27: Climate warming affects the phenology, local abundance and large‐scale distribution of plants and pollinators. Despite this, there is still limited knowledge of how elevated temperatures affect plant‐pollinator mutualisms and how changed availability of mutualistic partners influences the persistence of interacting species. Here we review the evidence of climate warming effects on plants and pollinators and discuss how their interactions may be affected by increased temperatures. The onset of flowering in plants and first appearance dates of pollinators in several cases appear to advance linearly in response to recent temperature increases. Phenological responses to climate warming may therefore occur at parallel magnitudes in plants and pollinators, although considerable variation in responses across species should be expected. Despite the overall similarities in responses, a few studies have shown that climate warming may generate temporal mismatches among the mutualistic partners. Mismatches in pollination interactions are still rarely explored and their demographic consequences are largely unknown. Studies on multi‐species plant‐pollinator assemblages indicate that the overall structure of pollination networks probably are robust against perturbations caused by climate warming. We suggest potential ways of studying warming‐caused mismatches and their consequences for plant‐pollinator interactions, and highlight the strengths and limitations of such approaches. | H27: maybe | I27: Hayashi | J27: No | N27: The study did not evaluate range shift. | O27: Ecology letters | P27: 2009 | Q27: SJ Hegland, A Nielsen, A Lázaro, AL Bjerknes… | R27: 10.1111/j.1461-0248.2008.01269.x
B28: E184 | C28: =LEFT(B28,1) & TEXT(RIGHT(B28,LEN(B28)-1),"0000") -> E0184 | D28: E0184 | E28: alpine | F28: Population fragmentation causes randomly fixed genotypes in populations of arabidopsis kamchatica in the japanese archipelago [erratum: march 2012 … | G28: Populations of arctic alpine plants likely disappeared and re-colonised several times at the southern edge of their distributions during glacial and interglacial cycles throughout the Quaternary. Range shift and population fragmentation after a glacial period would affect the genetic structure of such plants in southernmost populations. We aimed to elucidate how climatic oscillations influenced the population subsistence of alpine plants in the Japanese Archipelago as one of the southernmost populations, by inferring the genetic structure of Arabidopsis kamchatica subsp. kamchatica and the intraspecific littoral taxon, subsp. kawasakiana. We identified genotypes based on the haplotypes of five nuclear genes and two chloroplast DNA spacers for 164 individuals from 24 populations. Most populations harboured only one private genotype, whereas few polymorphisms were found in each population. Two genetic genealogies were found, suggesting that northern Japanese populations of alpine subsp. kamchatica, subsp. kawasakiana and the northerly subsp. kamchatica in eastern Russia and Alaska clustered and differentiated from populations in central Honshu, western Japan and Taiwan. During climatic oscillations, the genetic structure of extant southernmost populations would have been shaped by strong genetic drift under population fragmentation and randomly fixed to a single genotype among their ancestral polymorphisms. | H28: yes | I28: Hayashi | J28: No | N28: The study did not evaluate range shift. | O28: Journal of Plant Research | P28: 2012 | Q28: H Higashi, H Ikeda, H Setoguchi | R28: 10.1007/s10265-011-0443-9
B29: E218 | C29: =LEFT(B29,1) & TEXT(RIGHT(B29,LEN(B29)-1),"0000") -> E0218 | D29: E0218 | E29: alpine | F29: The relationship between mating system and genetic diversity in diploid sexual populations of cyrtomium falcatum in japan | G29: The impact of variation in mating system on genetic diversity is a well-debated topic in evolutionary biology. The diploid sexual race of Cyrtomium falcatum (Japanese holly fern) shows mating system variation, i.e., it displays two different types of sexual expression (gametangia formation) in gametophytes: mixed (M) type and separate (S) type. We examined whether there is variation in the selfing rate among populations of this species, and evaluated the relationship between mating system, genetic diversity and effective population size using microsatellites. In this study, we developed eight new microsatellite markers and evaluated genetic diversity and structure of seven populations (four M-type and three S-type). Past effective population sizes (Ne) were inferred using Approximate Bayesian computation (ABC). The values of fixation index (FIS), allelic richness (AR) and gene diversity (h) differed significantly between the M-type (FIS: 0.626, AR: 1.999, h: 0.152) and the S-type (FIS: 0.208, AR: 2.718, h: 0.367) populations (when admixed individuals were removed from two populations). Although evidence of past bottleneck events was detected in all populations by ABC, the current Ne of the M-type populations was about a third of that of the S-type populations. These results suggest that the M-type populations have experienced more frequent bottlenecks, which could be related to their higher colonization ability via gametophytic selfing. Although high population differentiation among populations was detected (FST = 0.581, F'ST = 0.739), there was no clear genetic differentiation between the M- and S-types. Instead, significant isolation by distance was detected among all populations. These results suggest that mating system variation in this species is generated by the selection for single spore colonization during local extinction and recolonization events and there is no genetic structure due to mating system. | H29: yes | I29: Hayashi | J29: No | N29: The study did not evaluate range shift. | O29: Plos one | P29: 2016 | Q29: R Imai, Y Tsuda, S Matsumoto, A Ebihara, Y Watano | R29: 10.1371/journal.pone.0163683
B30: E237 | C30: =LEFT(B30,1) & TEXT(RIGHT(B30,LEN(B30)-1),"0000") -> E0237 | D30: E0237 | E30: alpine | F30: Defining biotechnological solutions for insect control in sub‐saharan africa | G30: Africa is burdened by food insecurity with nearly a billion people suffering from starvation, undernutrition, and malnutrition. Climate change prediction models forecast changes in rainfall patterns and rising temperature regimes, with impacts particularly on Southern and East Africa. These predictions are especially concerning for the production of major food crops, such as maize, sorghum, millet, and groundnut, because median temperature increases are associated with increased pest pressure and changes in migratory patterns. These factors will result in significantly more pest invasions and an increased need for innovative insect management practices. This review focuses on pest control strategies, highlighting important examples, their economic impact, and new alternative pest control strategies. African policymakers remain hesitant to move forward with establishing biosafety laws and commercializing GM crops, and it is often difficult to implement regulatory measures in smallholder agriculture to increase efficacy. | H30: maybe | I30: Hayashi | J30: No | N30: The study did not evaluate range shift. | O30: Food and Energy Security | P30: 2020 | Q30: AM Botha, KJ Kunert, J Maling'a… | R30: 10.1002/fes3.191
B31: E238 | C31: =LEFT(B31,1) & TEXT(RIGHT(B31,LEN(B31)-1),"0000") -> E0238 | D31: E0238 | E31: alpine | F31: Modelling species distributions to map the road towards carnivore conservation in the tropics | G31: Knowing the distribution of species and the factors which determine it is a basic requirement for conservation efforts and developing management plans. Species distribution modelling (SDM) is a speedy and cost-effective tool for predicting species distributions, particularly for species in remote and inaccessible areas. This technique can be applied for example for poorly known small carnivore species in Southeast Asia, a biodiversity hot spot for mammals. SDM is used to gain ecological insights about the environmental factors that determine species distribution, and helps to identify the areas where a species can occur and where confl icts may arise. However, recent advances in statistical theory and computer processing have made SDM a somewhat complex, diverse, and confusing area of research. This review presents an overview over the different techniques of species distribution modelling, and databases needed to answer applied questions in carnivore conservation, particularly in the tropics. We guide the ecologist through different methods which have become established approaches in the scientifi c literature and through freely available resources on abiotic data (environmental layers) for conducting such studies. We summarise the steps involved in predictive species distribution modelling, where the (carnivore) occurrence data come from different resources (such as museum records, voluntary surveys, systematic surveys, etc.). Finally, we explore the applications of such predictions in carnivore conservation | H31: maybe | I31: Hayashi | J31: No | N31: The study did not evaluate range shift. | O31: The Raffles Bulletin of Zoology | P31: 2013 | Q31: R Kanagaraj, T Wiegand, A Mohamed… | R31: N/A
B32: E257 | C32: =LEFT(B32,1) & TEXT(RIGHT(B32,LEN(B32)-1),"0000") -> E0257 | D32: E0257 | E32: forest | F32: Complex range shifts among forest functional types under the contemporary warming | G32: The direction and magnitude of species distribution shifts tend to differ among species and functional types (FTs). Quantifying functional trait variation and species interactions will improve our understanding of the complex mechanisms that govern ecosystem dynamics and their responses to climate change. Here, we analyzed differences in the juvenile and adult temperature ranges of Japanese tree species at the mean, colder edge, and warmer edge of their distributions to reveal how functional traits affect interactions between different FT groups (e.g., deciduous and evergreen broad-leaved trees), using linear models and permutation tests. Overall, juveniles preferred cooler sites, but with high variation. The variation among species was partly explained by the difference in seed mass where species with lighter seeds tend to colonize colder sites. On the other hand, the distribution range of FTs showed complex behavior at the ecotones of different FTs. Specifically, in three of eight ecotones, nonparallel range shifts between FTs were detected, which includes cold shifting in deciduous broad-leaved FT where a warm shift by subalpine FT happened, and cold shifting in subtropical FT where warm shifts by either the deciduous broad-leaved or the evergreen broad-leaved FTs happened. Our results suggest that past warming has caused a general cold shift at species level, whereas different mechanisms, such as light seeds disperse farther in distribution's colder edge and heavy seeds (e.g., evergreen broad-leaved) compete better in warmer edge, create nonparallel responses of FT distribution ranges leading to the observed homogenization at several ecotones among FTs. These complex range shifts at FT level have crucial implications for climate change mitigation and adaptation. | H32: yes | I32: Hitomi(Jonathan) | J32: No | K32: Forest | N32: ある種に注目してはおらず、機能形質がどのように分布変化するかを調べている | O32: Global change biology | P32: 2022 | Q32: Koide, D; Yoshikawa, T; Ishihama, F; Kadoya, T | R32: 10.1111/gcb.16001
B33: E258 | C33: =LEFT(B33,1) & TEXT(RIGHT(B33,LEN(B33)-1),"0000") -> E0258 | D33: E0258 | E33: forest | F33: Climate change and the northward shift of cryptotympana facialis in japan: evidence from national survey data | G33: We developed a species distribution model of Cryptotympana facialis in Japan in order to investigate (1) the relationship between climate change and the northward shift of this species, (2) the existence of potential habitats in northern areas, and (3) the possibility of further northward shifts in the future. The distribution of C. facialis can be explained by life-history-related climate factors, including egg-hatching probability based on the sum of effective temperature, total precipitation during the rainy season, topographic slope, and the proportions of forest and urban areas, using an intrinsic Gaussian conditional autoregressive (CAR) model. The changes in potential habitat for C. facialis under climate change were projected using predicted climate conditions for 2070. In the parameter estimates of the CAR model, hatching probability, precipitation, and urban area were positive factors, while slope and forest area were negative factors. The fixed effects of the CAR model showed that more potential habitats exist in the north than in the current range of the species in western Japan. Moreover, our projection showed areas of suitable habitat increasing under all climate change scenarios. The current distribution of C. facialis is not in a state of equilibrium, possibly due to its low speed of dispersal. The distribution of C. facialis will expand to northern areas without climate warming, but climate warming will increase the amount of potential habitat. We emphasize the importance of considering life-history-related climatic factors, non-climatic factors, and spatial autocorrelation when modeling species distributions under climate change. | H33: maybe | I33: Hitomi(Jonathan) | J33: yes | K33: Forest, Urban area | L33: No | N33: クマゼミの分布変化 | O33: Climate research | P33: 2016 | Q33: Saito, MU; Kurashima, O; Ito, M | R33: 10.3354/cr01377
B34: E259 | C34: =LEFT(B34,1) & TEXT(RIGHT(B34,LEN(B34)-1),"0000") -> E0259 | D34: E0259 | E34: forest | F34: Predictions of kelp distribution shifts along the northern coast of Japan | G34: Japanese kelps are important because they perform a valuable ecosystem function of coastal kelp forest formation, and they are important food resources. The present study aimed to predict future shifts in major kelp species in northern Japan under different climate change scenarios. From a database of cold temperate kelp species in Japan, we extracted 1,958 data points to estimate the distribution of 11 kelp species that inhabit the waters around northern Japan. Distributions of the past (1980s) and the future (2040s and 2090s) were estimated using a species distribution model (MaxEnt). Variation in summer and winter sea surface temperatures was the factor most responsible for the estimated distribution patterns for most species; the length of natural rocky coasts and wave height were also important for some species. A forecast of shifts in distributions based on different Intergovernmental Panel on Climate Change scenarios showed that kelp species diversity in Japan would significantly decrease. By the 2090s, their habitat range overall was estimated to decline to 30-51% of that of the 1980s with moderate warming (Representative concentration pathways [RCP] 4.5) and to 0-25% with severe warming (RCP 8.5). The model predicted that 6 of 11 cold temperate kelp species may become extinct around Japan by the 2090s (RCP 8.5). Commercially important species, such as Saccharina japonica, are also expected to decline greatly, which may affect kelp fisheries and aquaculture in northern Japan. | H34: yes | I34: Hitomi(Jonathan) | J34: yes | K34: marine | L34: No | M34: Fig.2, Fig.3, Text | O34: Ecological research | P34: 2020 | Q34: Sudo, K; Watanabe, K; Yotsukura, N; Nakaoka, M | R34: 10.1111/1440-1703.12053
B35: E260 | C35: =LEFT(B35,1) & TEXT(RIGHT(B35,LEN(B35)-1),"0000") -> E0260 | D35: E0260 | E35: forest | F35: Predicted scarcity of suitable habitat for alpine plant communities in northern japan under climate change | G35: QuestionAlpine vegetation is sensitive to climate change, with shifts in species ranges, changes in community composition, and an upward shift in the forest limit over decades. Under climate change, habitats suitable for alpine vegetation will progressively decrease in scale, making their protection and conservation particularly important. In the Taisetsu Mountains of Japan, alpine vegetation has changed remarkably during the last decade. The aim of this study was to estimate the distribution of habitats suitable for alpine and subalpine vegetation types (snowbeds, shrubs, and alpine heathland/fellfield) and competing vegetation types (Sasa spp. and subarctic forest), while considering uncertainties in future predictions and climate scenarios. LocationTaisetsu Mountains, Daisetsuzan National Park, Hokkaido (northern Japan). MethodsWe estimated the habitat area suitable for each vegetation type from current vegetation maps on the basis of the predictions by three global climate models (GCMs) under two climate change scenarios (RCP2.6 and RCP8.5) using five habitat suitability models (HSMs) in two periods (2046-2050 and 2096-2100). We also compared the performances of the HSMs. ResultsMean summer temperature and snow-cover period had significant effects on the distribution of all vegetation types. The estimated distribution area for suitable habitat did not differ markedly among GCMs and HSMs. Under the RCP2.6 scenario, habitats suitable for snowbeds and alpine heathland/fellfield drastically decreased overall but were preserved in some regions. Under the RCP8.5 scenario, however, subarctic forest almost completely replaced alpine and subalpine vegetation types over time. ConclusionsOur projections indicate that the severity of future climate change will determine whether or not habitats suitable for alpine vegetation will remain. Monitoring the dynamics of endemic and rare species for the effects of global warming should be the priority for adaptation strategies to enable timely conservation measures. | H35: maybe | I35: Hitomi(Jonathan) | J35: maybe | K35: alpine | L35: No | O35: Applied vegetation science | P35: 2022 | Q35: Amagai, Y; Oguma, H; Ishihama, F | R35: 10.1111/avsc.12694
B36: E261 | C36: =LEFT(B36,1) & TEXT(RIGHT(B36,LEN(B36)-1),"0000") -> E0261 | D36: E0261 | E36: forest | F36: Probability distributions, vulnerability and sensitivity in fagus crenata forests following predicted climate changes in japan | G36: Question: How much is the probability distribution of Fagus crenata forests predicted to change under a climate change scenario by the 2090s, and what are the potential impacts on these forests? What are the main factors inducing such changes? Location: The major islands of Japan. Methods: A predictive distribution model was developed with four climatic factors (summer precipitation, PRS; winter precipitation, PRW; minimum temperature of the coldest month, TMC; and warmth index, WI) and five non-climatic factors (topography, surface geology, soil, slope aspect and inclination). A climate change scenario was applied to the model. Results: Areas with high probability (>0.5) were predicted to decrease by 91%, retreating from the southwest, shrinking in central regions, and expanding northeastwards beyond their current northern limits. A vulnerability index (the reciprocal of the predicted probability) suggests that Kyushu, Shikoku, the Pacific Ocean side of Honshu and southwest Hokkaido will have high numbers of many vulnerable F. crenata forests. The forests with high negative sensitivity indices (the difference between simulated probabilities of occurrence under current and predicted climates) mainly occur in southwest Hokkaido and the Sea of Japan side of northern Honshu. Conclusion: F. crenata forest distributions may retreat from some islands due to a high WI. The predicted northeastward shift in northern Hokkaido is associated with increased TMC and PRS. High vulnerability and negative sensitivity of the forests in southern Hokkaido are due to increased WI. | H36: maybe | I36: Hitomi(Jonathan) | J36: maybe | K36: forest | L36: No | N36: ブナについて、というよりはブナ林の変化 | O36: Journal of vegetation science | P36: 2004 | Q36: Matsui, T; Yagihashi, T; Nakaya, T; Taoda, H; Yoshinaga, S; Daimaru, H; Tanaka, N | R36: 10.1111/j.1654-1103.2004.tb02302.x
B37: E262 | C37: =LEFT(B37,1) & TEXT(RIGHT(B37,LEN(B37)-1),"0000") -> E0262 | D37: E0262 | E37: forest | F37: Changes in distribution ranges of abies species dominating in the forests of northeast asia since the last glacial maximum | G37: AimClimate variations within the stadial-interstadial cycles drive shifts in the distribution of forest dominants. This study examines how climate dynamic alters the distribution ranges of two boreal and one cold-temperate Abies species dominating in Northeast Asia.LocationNortheast Asia: China, Japan, Korea and Russia.TaxonAbies nephrolepis, A. sachalinensis (sect. Balsamea) and A. holophylla (sect. Pseudopicea).MethodsWe developed climate envelope species distribution models (SDMs) using warmth and coldness indices, the continentality index, and proxies of rain and snow precipitation indices. We interpolated SDMs on reconstructed climates for the Last Glacial Maximum (LGM) and the Holocene Climatic Optimum (HCO) and to predicted climates for 2070 under global warming scenarios RCP2.6 and RCP8.5.ResultsDuring the LGM, the climatic optimum for all species covered extensive areas on the shelves of the Japanese and Yellow Seas, facilitated by the global sea level drop. The interglacial climatic optimum supports the expansion of A. nephrolepis and A. sachalinensis compared to the LGM, whereas the range of A. holophylla climatic niche range experiences a reduction.Main ConclusionsOur findings highlight the significant impact of climatic oscillations on the spatial distribution and ecological dynamics of Abies species in Northeast Asia. The contrasting responses of boreal and temperate fir species to glacial and interglacial periods underscore the complex interplay between climate change and the distribution of forest dominants. Projections under future warming scenarios suggest that Abies species will face further range shifts, emphasising the need for adaptive forest management and conservation strategies, especially in the southern part of their distribution. | H37: yes | I37: Hitomi(Jonathan) | J37: maybe | K37: forest | L37: No | O37: Journal of biogeography | P37: 2025 | Q37: Petrenko, T; Dzizyurova, V; Altman, J; Dolezal, J; Kislov, D; Korznikov, K | R37: 10.1111/jbi.15057
B38: E267 | C38: =LEFT(B38,1) & TEXT(RIGHT(B38,LEN(B38)-1),"0000") -> E0267 | D38: E0267 | E38: forest | F38: Environmental dependence of population dynamics and height growth of a subalpine conifer across its vertical distribution: an approach using high-resolution aerial photographs | G38: Many studies have reported shifts in the altitudinal ranges of plant species in response to recent global warming. However, most studies of tree species have been conducted on a small scale and have focused on tree line ecotones by examining tree rings and age structure on account of the long life spans of the trees. To examine the impact of climate change on forest dynamics at a regional scale, we investigated differences in the population density and canopy height of a Japanese subalpine coniferous species, Abies mariesii, between 1967 and 2003 by analysis of high-resolution aerial photographs of the Hakkoda Mountains, Honshu, Japan. In 712 plots within the photographs we analyzed which environmental variables (including elevation, aspect, wetness, and distance from moorlands) account for these changes. The population density of A. mariesii decreased below 1000 m a.s.l. and increased above 1300 m a.s.l. It also increased around moorlands, which may provide refugia at low elevations. The rate of increase in canopy height was lowest on the southeastern slopes and on the periphery of the moorlands. The distinct changes in the population density of A. mariesii at its distribution limits probably reflect the responses of the population to climatic changes during three decades. Areas surrounding the moorlands may offer refugia in spite of the poor growing conditions there. | H38: maybe | I38: Hitomi(Jonathan) | J38: maybe | K38: forest,alpine | L38: yes | M38: Table 1, Text | O38: Global change biology | P38: 2011 | Q38: Shimazaki, M; Sasaki, T; Hikosaka, K; Nakashizuka, T | R38: 10.1111/j.1365-2486.2011.02491.x
B39: E271 | C39: =LEFT(B39,1) & TEXT(RIGHT(B39,LEN(B39)-1),"0000") -> E0271 | D39: E0271 | E39: forest | F39: Regeneration of subalpine conifer species is inhibited by bark-stripping deer in a betula forest | G39: Climate change is expected to alter biotic interactions governing tree species ranges. Identifying the limiting demographic processes controlling tree distribution is key to projecting future range shifts. A preference by herbivores for stripping the bark of tree species undergoing range shifts could inhibit tree range shifts. We focused on the effects of bark stripping by recently arrived sika deer (Cervus nippon) on the survival of subalpine conifers (Abies spp.) in a Betula ermanii forest in central Japan. Abies spp. which currently occur at lower elevations than B. ermanii but are predicted to expand to higher elevations with climate change, were less abundant than B. ermanii on Mt. Kita, central Japan, and were preferred by sika deer for bark stripping. The ratio of the number of stripped Abies stems to the total number of stripped stems was unrelated to elevation. Because of the lower dominance of Abies spp. at higher elevations, bark-stripping pressure on them would be stronger there. Both bark stripping by deer and competition (intra- and interspecific) contribute to the death of Abies spp. Our results suggest that bark-stripping herbivores can be an important contributing factor hampering upward range shifts of Abies spp. | H39: yes | I39: Nana(Jonathan) | J39: No | K39: forest | N39: シカによる樹皮剥ぎが、亜高山帯の針葉樹の将来的な分布拡大を阻害する可能性を調査した研究 | O39: Arctic antarctic and alpine research | P39: 2025 | Q39: Nagaike, T; Iijima, H | R39: 10.1080/15230430.2024.2447631
B40: E272 | C40: =LEFT(B40,1) & TEXT(RIGHT(B40,LEN(B40)-1),"0000") -> E0272 | D40: E0272 | E40: forest | F40: Climate-driven divergent long-term trends of forest beetles in japan | G40: Concerning declines in insect populations have been reported from Europe and the United States, yet there are gaps in our knowledge of the drivers of insect trends and their distribution across the world. We report on our analysis of a spatially extensive, 14-year study of ground-dwelling beetles in four natural forest biomes spanning Japan's entire latitudinal range (3000 km). Beetle species richness, abundance and biomass declined in evergreen coniferous forests but increased in broadleaf-coniferous mixed forests. Further, beetles in evergreen coniferous forests responded negatively to increased temperature and precipitation anomalies, which have both risen over the study's timespan. These significant changes parallel reports of climate-driven changes in forest tree species, providing further evidence that climate change is altering forest ecosystems fundamentally. Given the enormous biodiversity and ecosystem services that forests support globally, the implications for biodiversity change resulting from climate change could be profound. | H40: yes | I40: Nana(Jonathan) | J40: No | K40: forest | N40: 気候変動が森林生態系に与える影響を広く調査した研究、北上に関する記載なし | O40: Ecology letters | P40: 2022 | Q40: Evans, MJ; Barton, P; Niwa, S; Soga, M; Seibold, S; Tsuchiya, K; Hisano, M | R40: 10.1111/ele.14082
B41: E274 | C41: =LEFT(B41,1) & TEXT(RIGHT(B41,LEN(B41)-1),"0000") -> E0274 | D41: E0274 | E41: forest | F41: Formation of disjunct plant distributions in northeast asia: a case study of betula davurica using a species distribution model | G41: Repeated climate change during glacial and interglacial periods of the Quaternary led to mass migrations that resulted in disjunct distributions for many species. However, few studies have examined the processes that form disjunct distributions in Northeast Asia (NEA). In this study, we examined the disjunct distribution of Betula davurica Pall. in the Japanese archipelago. This species is a dominant canopy tree found in cool-temperate deciduous broad-leaved forests of continental NEA. We hypothesized that Quaternary climate change caused the present disjunct distribution pattern of this species. To test this hypothesis, we adopted a species distribution model and examined a series of potential habitats in the Last Glacial Maximum (LGM), the mid-Holocene, and the present. We generated models in MaxEnt with B. davurica presence as the response variable and six bioclimatic variables as predictor variables. During the LGM, projected potential habitats were distributed around the Korean Peninsula, East China, and the Japanese archipelago, excluding Hokkaido. In the mid-Holocene, habitats retreated both from East China and western Japan, remained unchanged in the Korean Peninsula and central Honshu mountains, and expanded to northern China, the Russian Far East, as well as northern Japan (Hokkaido). Thus, post-LGM global warming led to an expansion of B. davurica distribution to northern parts of continental NEA, along with a retreat in the Japanese archipelago. This shift in populations formed the present disjunct distribution. | H41: yes | I41: Nana(Jonathan) | J41: maybe | K41: forest | L41: No | N41: 韓国半島、中国東部も含むアジア圏全体におけるBetula davurica Pall.の移動に関する研究 | O41: Plant ecology | P41: 2018 | Q41: Shitara, T; Nakamura, Y; Matsui, T; Tsuyama, I; Ohashi, H; Kamijo, T | R41: 10.1007/s11258-018-0862-y
B42: E276 | C42: =LEFT(B42,1) & TEXT(RIGHT(B42,LEN(B42)-1),"0000") -> E0276 | D42: E0276 | E42: forest | F42: Loss of habitat suitability and distribution range of the endangered japanese giant salamander under climate change | G42: Giant salamanders are the world's largest amphibians and keystone predators in riverine ecosystems where they face global declines. Identifying environmental variables influencing their distribution is, therefore, an essential step for their conservation. This study aims to assess the current habitat suitability and distribution of the Japanese giant salamander (Andrias japonicus) and to predict changes under future climate scenarios. We used species distribution models (SDMs) over a 282,916 km(2) area, including 477 high-resolution occurrence data of giant salamanders and seven remote-sensing environmental predictors (climatic, topographic and land use). We projected the prediction maps, identified the most contributing variables and calculated the shifts of suitable areas for three periods (2050, 2070 and 2090) under projected climatic conditions. Climatic variables highly contributed to the distribution of giant salamanders (76% of the total), with preferences for areas with moderate precipitations during cold and wet seasons and mild summer temperatures. A moderately steep surrounding environment was favourable for salamanders, whereas the land-use variables had less influence. Future climate predictions indicate a major decrease of suitable areas. Altogether, our results highlight the habitat preferences of giant salamanders at a broad scale and the negative impact of climate change on future suitable areas. These findings provide important steps for upcoming conservation actions for this threatened species in delineating favourable distribution ranges and priority areas that should be directly affected by climate change. Finally, they emphasise the need for new research at a fine scale on disturbances to the aquatic habitat to enhance the conservation of giant salamanders. | H42: maybe | I42: Nana(Jonathan) | J42: No | K42: marine | N42: オオサンショウウオ将来の生息適地が大幅に減少することを予測した研究 | O42: Frontiers of biogeography | P42: 2025 | Q42: Duret, C; Bartet, T; Hambuckers, A; Kishida, O; Okada, S; Taguchi, Y; Takahashi, MK; Denoël, M | R42: 10.21425/fob.18.133105
B43: E277 | C43: =LEFT(B43,1) & TEXT(RIGHT(B43,LEN(B43)-1),"0000") -> E0277 | D43: E0277 | E43: forest | F43: Rapid loss of temperate kelp forests revealed by unmanned aerial vehicle (uav) photography and underwater observations | G43: Climate-related increases in ocean temperature, herbivore abundance, and the frequency of extreme weather events have triggered phase shifts from kelp forests to deforested barrens. While unmanned aerial vehicle (UAV) photography is now an effective method for monitoring marine environments, few studies have used it to detect changes in submerged marine forests. To investigate changes in kelp forests formed by Ecklonia cava under the influence of ocean warming and large typhoons, we conducted UAV photography in two areas (70,755 and 116,199 m(2)) and underwater visual surveys along two transects off the Manazuru coast of central Japan (35 degrees 09'N) between 2019 and 2020. UAV photography revealed a complete loss of the kelp forests (34,042 and 48,641 m(2)) there from 2019 to 2020. The underwater visual census revealed a change in benthic communities, with a 57.3 % decrease in Ecklonia cover and an 11.3 % increase in small and coralline algae cover during this period. Based on the wave height during the passage of Typhoon Hagibis in fall 2019, ocean warming since 2008, and the prolonged period of high temperature (> 16 degrees C) from fall 2019 autumn to winter 2020, we speculated that the phase shift from Ecklonia beds to deforested barrens was due to the synergistic effects of the typhoon, ocean warming, and enhanced fish herbivory due to high temperature. Our results demonstrate the utility of UAV photography for monitoring submerged kelp forests, and combined results with previous studies suggest that the distribution of the phase shifts has expanded to higher latitudes in Japan. | H43: yes | I43: Nana(Jonathan) | J43: No | K43: marine | N43: ドローン撮影を用いて、日本の藻場がわずか1年で完全に消失した実態を明らかにした研究 | O43: Aquatic botany | P43: 2025 | Q43: Sato, M; Kinoshita, J; Ishita, K; Arima, S; Fudo, M; Kuwahara, H | R43: 10.1016/j.aquabot.2025.103900
B44: E280 | C44: =LEFT(B44,1) & TEXT(RIGHT(B44,LEN(B44)-1),"0000") -> E0280 | D44: E0280 | E44: forest | F44: The elevational distribution of fagus crenata regeneration at low elevations in the shirakami mountains, a world natural heritage site in japan | G44: The Shirakami Mountains are a World Natural Heritage site because of their vast beech (Fagus crenata) forests and high diversity of flora and fauna. As global warming progresses, the area suitable for F. crenata growth is expected to shift from low to higher elevations. However, no studies have examined the current elevational distribution of the species' regeneration. Here, we investigated the amount of F. crenata regeneration in the Shirakami Mountains and compared this amount among different elevations. Our nine study sites covered forests ranging from 269 m to 662 m, which covers the low to middle parts of the elevational distribution of F. crenata. At each site, we established three 20 m x 20 m plots and conducted a tree census. We approximated the regeneration density as a function of the diameter at breast height (DBH) distribution of F. crenata at each site using a power function: density = a DBHb. We found that a and b decreased and increased, respectively, as elevation decreased. Generalized linear mixed model analysis also indicated that decreasing elevation significantly decreased the number of seedlings of F. crenata. These results suggest decreasing regeneration at low elevation. Although it is difficult to identify the main causes of this pattern, we predict that regeneration may become even poorer if climate warming continues. Long-term monitoring along elevational clines will help us track the detailed effects of global warming on the beech forests. | H44: maybe | I44: Nana(Jonathan) | J44: No | K44: forest | N44: 標高の違いがブナの苗木の育ちやすさに与える影響 | O44: Journal of forest research | P44: 2024 | Q44: Inomata, T; Saeki, I | R44: 10.1080/13416979.2023.2294510
B45: E282 | C45: =LEFT(B45,1) & TEXT(RIGHT(B45,LEN(B45)-1),"0000") -> E0282 | D45: E0282 | E45: forest | F45: Surviving winter: diapause syndrome in the southern green stink bug nezara viridula in the laboratory, in the field, and under climate change conditions | G45: The southern green stink bug Nezara viridula (L.) (Heteroptera: Pentatomidae) has long attracted attention not only as a serious pest of numerous agricultural crops, but also as a species expanding its range in many parts of the world. Nezara viridula has also been widely used as a model in different experimental studies. The present review focuses on reproductive (i.e. adult) winter diapause, which is the pivotal element of the species' seasonal cycle. Results from numerous field experiments and observations, as well as laboratory ecophysiological investigations conducted during the few last decades, are analyzed and interpreted. Experimental findings are used to describe in detail the dynamics of physiological changes during overwintering. Reproductive diapause in N. viridula is controlled in both sexes by photoperiodic conditions. The induction of diapause is associated with a reversible change of body colour from green or yellow to russet (or brown). The proper timing of adult emergence and the induction of diapause, as well as the size of adults, is vitally important for successful overwintering. Nezara viridula has been shown to respond strongly to the current trend in climate change by shifting the limit of its northern range, particularly in central Japan. Analysis of historic climate data suggests that the environmental conditions during the last few decades have become more favourable for the overwintering survival of N. viridula in many locations in central Japan. This has likely promoted the northward spread of the species. The relationships between reproductive diapause, reversible body colour change, overwintering success and the recent range expansion are analyzed. Perspectives of the range dynamics of the species are discussed in light of further predicted climate change. | H45: yes | I45: Nana(Jonathan) | J45: maybe | K45: other: cropland | L45: No | N45: ミナミミドリカメムシの「休眠の仕組み」を解明した研究で、北上に関する話も出てくるが、E400の引用のみ。 | O45: Physiological entomology | P45: 2012 | Q45: Musolin, DL | R45: 10.1111/j.1365-3032.2012.00846.x
B46: E284 | C46: =LEFT(B46,1) & TEXT(RIGHT(B46,LEN(B46)-1),"0000") -> E0284 | D46: E0284 | E46: forest | F46: Range shift and introgression of three japanese abies species: insights from population genetic data and species distribution modeling | G46: Range shifts during the Pleistocene shaped the unique phylogeographical structures of many species. Pleistocene range shifts gave currently allopatric species opportunities to occur in sympatry, likely resulting in ancient introgressions between related taxa. In our study, we investigate the range shifts and introgression patterns of three Japanese Abies species (A. firma, A. homolepis, and A. veitchii) by employing an extensive survey of 43 populations. This survey includes comprehensive analysis of both mitochondrial (mtDNA) and nuclear (18 microsatellites) genomes, in combination with species distribution modeling (SDM). It is important to note that these two types of markers provide distinct and complementary information, as they have different modes of inheritance and mutation rates. Bayesian clustering analysis indicates that the three species were clearly separated, with the exception of the A. homolepis var. umbellata population, which is considered a natural hybrid between A. homolepis and A. firma. However, mtDNA haplotypes of the four northern populations of A. firma were entirely replaced by two major haplotypes of A. homolepis and A. veitchii. The results of neighbor-net, NewHybrids, STRUCTURE analyses, and SDM suggest that historical introgression between species occurred in each geographic region, with mtDNA capture being the likely mechanism. However, contrary to these findings, the ABC coalescent analysis did not support an ancient introgression. Therefore, further validation with genome-wide level data is needed to clarify this issue. Our conclusion is that climate-induced range shifts during the Pleistocene/Holocene likely played a crucial role in the observed patterns of introgression in these species. | H46: yes | I46: Fatima(Jonathan) | J46: Maybe | K46: Temperate forest (Subalpine–Montane coniferous forest) | L46: No | M46: Text / Figures (SDM results) / Table 1 | N46: Historical (Pleistocene/Holocene) and inferred range shifts; no quantitative metrics (e.g., km, elevation, rate); focus on introgression/phylogeography, not measurable redistribution. | O46: Tree genetics & genomes | P46: 2023 | Q46: Uchiyama, K; Fujii, S; Tsuyama, I; Tanaka, N; Setsuko, S; Kimura, MK; Suyama, Y; Tsumura, Y | R46: 10.1007/s11295-023-01617-7
B47: E288 | C47: =LEFT(B47,1) & TEXT(RIGHT(B47,LEN(B47)-1),"0000") -> E0288 | D47: E0288 | E47: forest | F47: Temperate macroalgae impacts tropical fish recruitment at forefronts of range expansion | G47: Warming waters and changing ocean currents are increasing the supply of tropical fish larvae to temperature regions where they are exposed to novel habitats, namely temperate macroalgae and barren reefs. Here, we use underwater surveys on the temperate reefs of south-eastern (SE) Australia and western Japan (similar to 33.5A degrees N and S, respectively) to investigate how temperate macroalgal and non-macroalgal habitats influence recruitment success of a range of tropical fishes. We show that temperate macroalgae strongly affected recruitment of many tropical fish species in both regions and across three recruitment seasons in SE Australia. Densities and richness of recruiting tropical fishes, primarily planktivores and herbivores, were over seven times greater in non-macroalgal than macroalgal reef habitat. Species and trophic diversity (K-dominance) were also greater in non-macroalgal habitat. Temperate macroalgal cover was a stronger predictor of tropical fish assemblages than temperate fish assemblages, reef rugosities or wave exposure. Tropical fish richness, diversity and density were greater on barren reef than on reef dominated by turfing algae. One common species, the neon damselfish (Pomacentrus coelestis), chose non-macroalgal habitat over temperate macroalgae for settlement in an aquarium experiment. This study highlights that temperate macroalgae may partly account for spatial variation in recruitment success of many tropical fishes into higher latitudes. Hence, habitat composition of temperate reefs may need to be considered to accurately predict the geographic responses of many tropical fishes to climate change. | H47: yes | I47: Fatima(Jonathan) | J47: No | K47: Marine (temperate rocky reef / macroalgal reef) | L47: No | M47: Text / Figures / Tables | N47: Quantitative data present, but only for recruitment and community structure | O47: Coral reefs | P47: 2017 | Q47: Beck, HJ; Feary, DA; Nakamura, Y; Booth, DJ | R47: 10.1007/s00338-017-1553-1
B48: E289 | C48: =LEFT(B48,1) & TEXT(RIGHT(B48,LEN(B48)-1),"0000") -> E0289 | D48: E0289 | E48: forest | F48: The evolution of coral reef under changing climate: a scientometric review | G48: In this scientometric review, we employ the Web of Science Core Collection to assess current publications and research trends regarding coral reefs in relation to climate change. Thirty-seven keywords for climate change and seven keywords for coral reefs were used in the analysis of 7743 articles on coral reefs and climate change. The field entered an accelerated uptrend phase in 2016, and it is anticipated that this phase will last for the next 5 to 10 years of research publication and citation. The United States and Australia have produced the greatest number of publications in this field. A cluster (i.e., focused issue) analysis showed that coral bleaching dominated the literature from 2000 to 2010, ocean acidification from 2010 to 2020, and sea-level rise, as well as the central Red Sea (Africa/Asia), in 2021. Three different types of keywords appear in the analysis based on which are the (i) most recent (2021), (ii) most influential (highly cited), and (iii) mostly used (frequently used keywords in the article) in the field. The Great Barrier Reef, which is found in the waters of Australia, is thought to be the subject of current coral reef and climate change research. Interestingly, climate-induced temperature changes in “ocean warming” and “sea surface temperature” are the most recent significant and dominant keywords in the coral reef and climate change area. | H48: maybe | I48: Fatima(Jonathan) | J48: No | K48: Marine (coral reef) | L48: No | M48: Text | N48: This is a scientometric review (bibliometric analysis of literature), not an empirical study. It does not contain primary data on species distributions. | O48: Animals | P48: 2023 | Q48: Thirukanthan, CS; Azra, MN; Lananan, F; Sara, G; Grinfelde, I; Rudovica, V; Vincevica-Gaile, Z; Burlakovs, J | R48: 10.3390/ani13050949
B49: E297 | C49: =LEFT(B49,1) & TEXT(RIGHT(B49,LEN(B49)-1),"0000") -> E0297 | D49: E0297 | E49: forest | F49: Review: A comprehensive overview of studies related to the ecology and genetics of fagus crenata blume (siebold's beech, japanese beech) at the species' northernmost range limit | G49: Temperate forest species, including Fagus crenata Blume, have been experiencing distributional shifts during the climate oscillation throughout the Holocene epoch. This review describes the distinctive context of F. crenata populations at the northern range from the perspective of past distribution shifts, future expansion predictions, biotic and abiotic interactions in population establishment, forest vegetation characteristics, and genetic diversity during the expansion process. The current northern distribution limit of F. crenata is in southern Hokkaido and Okushiri Islands. Since 1900, a dozen of northern limit hypotheses has advocated the presence of restriction factors; however, the species shows signs of expanding its habitat northward at present. The current northern limit is not determined by physiological limitations because of the fact that artificial plantations of F. crenata grow well beyond its range. Several studies regarding climate scenarios have predicted species persistence in the future. Sociological studies revealed that a decline in vegetation units is observed from the southern to the northern populations on the Oshima Peninsula, Hokkaido. Also, vegetation on Okushiri Island includes remnants of warm temperate flora indicating a physiographic constraint of the F. crenata forest on the island, reflecting a past distributional shift. Most of the current northern marginal populations were revealed to be established at the time of large forest disturbance. The genetic diversity of local populations has been lost during the northward distribution shift due to the founder effect in the colonizing process. Then, the gene flow from rearward populations has dwindled by the completion of the population establishment. | H49: yes | I49: Fatima(Jonathan) | J49: No | K49: Temperate forest (cool-temperate deciduous forest) | L49: No | M49: Text | N49: Review paper; discusses historical and ongoing northward expansion and genetic/population dynamics | O49: Ecological research | P49: 2023 | Q49: Kitamura, K; Matsui, T; Kobayashi, M; Namikawa, K | R49: 10.1111/1440-1703.12356
B50: E299 | C50: =LEFT(B50,1) & TEXT(RIGHT(B50,LEN(B50)-1),"0000") -> E0299 | D50: E0299 | E50: forest | F50: Middle pleistocene climate change influenced northward divergence and cold adaptation in an asian lady's slipper orchid, cypripedium macranthos sw. (Orchidaceae) | G50: The Pleistocene was characterized by climate fluctuations with rapid transitions between glacial and interglacial periods. East Asia's land bridge dynamics and monsoon system during the Middle Pleistocene transition (MPT) further constrained species distributions and dispersals, which promoted local adaptation and species diversification, making East Asia an excellent location to study species biogeography. Cypripedium macranthos Sw., a terrestrial orchid, diverged in the Pleistocene and became widespread in Russia, China, Korea, and Japan. Many populations are now at risk due to illegal harvesting or habitat loss. With comprehensive sampling including 171 individuals among 22 populations across the entire distribution range, together with plastid DNA sequencing, we have explored the origin and impact of palaeoclimate on its spatial genetic structure and historical biogeography. Regression-based analyses commonly used in landscape genetics were also applied to investigate the effects of precipitation, temperature, and wind on gene flow. The results revealed northeastern China as the probable cradle of C. macranthos, with northeastward divergence and range expansion during the MPT, aided by monsoon shifts and wind-driven seed dispersal. Isolation by environment was detected with winter temperature as a driver for north-south divergence controlling for an effect of isolation by distance, revealing cold adaptation of the northern populations or temperature-driven genetic differentiation. We also emphasize the founder speciation of an unique variety on Rebun Island of Japan. The widespread but genetically and ecologically divergent C. macranthos populations highlight the need for more conservation attention on northern populations under global warming. | H50: yes | I50: Fatima(Jonathan) | J50: No | K50: Temperate terrestrial (forest understory / grassland) | L50: No | M50: Text / Figures | N50: Historical/inferred range expansion from genetic data | O50: Botanical journal of the linnean society | P50: 2024 | Q50: Chang, JT; Zhang, Y; Andronova, E; Averyanov, L; Filippov, EG; Kawahara, T; Shefferson, R; Kim, JH; Hsu, RCC; Cho, YH; Luo, MX; Liao, PC; Lee, Y | R50: 10.1093/botlinnean/boae003
B51: E300 | C51: =LEFT(B51,1) & TEXT(RIGHT(B51,LEN(B51)-1),"0000") -> E0300 | D51: E0300 | E51: forest | F51: Spatiotemporal recruitment patterns of two introduced magnolia l. species in a disturbed oak forest | G51: Although nearly half of all Magnolia species are threatened globally, human-assisted movement and cultivation of some species has led to their escape within non-indigenous ecosystems. The ongoing naturalization of select Magnolia taxa has been associated with climate change and variously characterized as assisted-migration, range shift/expansion, or biological invasion. This study documented recruitment patterns in space and time for two species of introduced 'umbrella' magnolias, which have become increasingly prolific in New England. A census was conducted that identified a total of 388 Magnolia macrophylla (SE US.) and M. obovata (Japan) individuals that escaped from cultivation and colonized an adjacent oak forest. Seedling recruitment occurred rapidly in response to forest disturbance, and mean tree age was significantly different as a function of three discrete disturbance events. M. obovata was a more successful colonizer overall, yielding more individuals (326 vs. 62), and recruiting further (90% quantile = 388 +/- 91 vs. 228 +/- 44 m) than M. macrophylla, given founding populations that were of identical size (n = 3) and similar age. This study represents the first documented escape of M. obovata in North America, while M. macrophylla has been documented elsewhere in New England and linked to increased temperature and precipitation patterns. | H51: yes | I51: Fatima(Jonathan) | J51: No | K51: Temperate forest (disturbed oak forest) | L51: No | M51: Text / Figures / Tables | N51: Focus is on local spread and recruitment within a forest | O51: Ecoscience | P51: 2020 | Q51: Rounsaville, TJ | R51: 10.1080/11956860.2020.1753311
B52: E301 | C52: =LEFT(B52,1) & TEXT(RIGHT(B52,LEN(B52)-1),"0000") -> E0301 | D52: E0301 | E52: forest | F52: Indicator plant species selection for monitoring the impact of climate change based on prediction uncertainty | G52: To develop a long-term volunteer-based system for monitoring the impacts of climate change on plant distributions, potential indicator plants and monitoring sites were assessed considering habitat prediction uncertainty. We used species distribution models (SDMs) to project potential habitats for 19 popular edible wild plants in Japan. Prediction uncertainties of SDMs were assessed using three high-performance modeling algorithms and 19 simulated future climate data. SDMs were developed using presence/absence records, four climatic variables, and five non-climatic variables. The results showed that prediction uncertainties for future climate simulations were greater than those from the three different modeling algorithms. Among the 19 edible wild plant species, six had highly accurate SDMs and greater changes in occurrence probabilities between current and future climate conditions. The potential habitats of these six plants under future climate simulations tended to shift northward and upward, with predicted losses in potential southern habitats. These results suggest that these six plants are candidate indicators for long-term biological monitoring of the impacts of climate change. If temperature continuously increases as predicted, natural populations of these plants will decline in Kyushu, Chugoku and Shikoku districts, and in low altitudes of Chubu and Tohoku districts. These results also indicate the importance of occurrence probability and prediction uncertainty of SDMs for selecting target species and site locations for monitoring programs. Sasa kurilensis, a very popular and widespread dominant scrub bamboo in the cool-temperate regions of Japan, was found to be the most effective plant for monitoring. (C) 2013 Elsevier Ltd. All rights reserved. | H52: yes | I52: Fatima(Jonathan) | J52: No | K52: Temperate forest (cool-temperate vegetation) | L52: No | M52: Text / Figures | N52: SDM-based projected shifts only | O52: Ecological indicators | P52: 2013 | Q52: Higa, M; Nakao, K; Tsuyama, I; Nakazono, E; Yasuda, M; Matsui, T; Tanaka, N | R52: 10.1016/j.ecolind.2013.01.010
B53: E303 | C53: =LEFT(B53,1) & TEXT(RIGHT(B53,LEN(B53)-1),"0000") -> E0303 | D53: E0303 | E53: forest | F53: Long-term variability in the fish assemblage around japan over the last century and early warning signals of regime shifts | G53: The marine ecosystems around Japan are very productive and have typical wasp-waist structure dominated by small pelagic fishes such as sardine, exhibiting large low-frequency fluctuations in biomass. Whereas studies on the variability in abundance of individual species such as sardine and anchovy are popular, only a few studies focused on the long-term variability of fish assemblage around Japan. In this study, 13 species/taxa ranging from small forage to large predatory species and from warm- to cold-water species were selected to indicate essential characteristics of the fish assemblage and their drivers were analysed based on fishery, oceanographic and climatic data sets from 1901 to 2018. Results show that two outstanding peaks during the 1930s and 1980s were characterized by abundant sardine. Additionally, species composition showed high similarities during similar temperature regimes while exhibiting contrasts during different temperature regimes. Variations and regime shifts in dominant patterns and fish community indices coincided well with the Atlantic Multidecadal Oscillation (AMO) and regional sea surface temperature (SST). Furthermore, gradient forest analysis identified AMO and regional SSTs as most important predictors of dominant patterns and fish community indices, suggesting that the decadal and multidecadal variability in the fish assemblage around Japan was forced by basin-scale climate variability as inherent in the AMO through its connections with regional SSTs. Autocorrelation coefficient demonstrated that the ecological indicators have the potential to be early warning signals of regime shifts, which suggests the possibility of coming cold regime since around 2015 and has important implications for fisheries management. | H53: maybe | I53: Haruka(Jonathan) | J53: maybe | K53: marine | L53: no | N53: Factors influencing long-term fluctuations in fish communities composition | O53: Fish and fisheries | P53: 2023 | Q53: Tian, YJ; Fu, CH; Yatsu, A; Watanabe, Y; Liu, Y; Li, JC; Liu, D; Pang, YM; Cheng, JH; Ho, CH; Ma, SY | R53: 10.1111/faf.12754
B54: E307 | C54: =LEFT(B54,1) & TEXT(RIGHT(B54,LEN(B54)-1),"0000") -> E0307 | D54: E0307 | E54: forest | F54: Temperate deciduous broadleaf forest dynamics around the last glacial maximum in a hilly area in the northern kanto district, central japan | G54: Research into the geographical distribution of temperate tree refugia and their associated environmental conditions during glacial stages is necessary to understand the processes by which the present vegetation and plant distributions developed. On the basis of pollen and plant macrofossil assemblages deposited in a small valley in a hill in the northern Kanto district in central Japan, we reconstructed the local and regional vegetation changes in and around the distribution range limit of temperate broadleaf trees during the latest stage of marine isotope stage (MIS) 3 (36.2–32.8 ka) and around the late stage of the last glacial maximum (LGM) (23.4–16.6 ka). During the latest stage of MIS 3, the local and regional vegetation in and around the hill was composed of temperate deciduous broadleaf forest dominated by Quercus subgen. Lepidobalanus and mixed with pinaceous conifers. The proportion of deciduous broadleaf trees in the regional vegetation increased during recurring warm and humid phases that were correlated with Greenland D-O 7, 6, and 5 warming events. During the LGM, coniferous forests composed of Picea jezoensis var. hondoensis, Tsuga diversifolia, Abies veitchii, and Betula ermanii, which are major components of the present subalpine forests in central and western Japan, expanded in hilly and mountain zones in central Japan. Refugia of temperate broadleaf trees existed at altitudes up to that of the study site and were limited to mesic places along the valley bottom. At the termination of the LGM around 18.8 ka, a biome shift to mixed coniferous and deciduous broadleaf forest dominated by Betula occurred in and around the study site. The expansion of deciduous broadleaf trees at ca. 19 ka, which has also been recognized in other localities in central Japan, may have been triggered by an increase in precipitation during the stage wherein summer insolation became greater. The temperate broadleaf trees that have been distributed in hilly-zone refugia were sensitive to warming at the termination of the LGM. | H54: yes | I54: Haruka(Jonathan) | J54: no | K54: forest | L54: no | N54: Ice age | O54: Quaternary international | P54: 2017 | Q54: Nishiuchi, R; Momohara, A; Osato, S; Endo, K | R54: 10.1016/j.quaint.2017.03.004
B55: E313 | C55: =LEFT(B55,1) & TEXT(RIGHT(B55,LEN(B55)-1),"0000") -> E0313 | D55: E0313 | E55: forest | F55: The dynamics and geographic disjunction of the kelp eisenia arborea along the west coast of canada | G55: Eisenia arborea has a disjunct distribution along the west coast of North America. We detail the current distribution of E. arborea and use long-term records to examine how present-day shifts in E. arborea prevalence and abundance in British Columbia (BC), relative to the dominant stipitate kelp Pterygophora californica, may be driven by interactions between changing grazing pressure and warming water. We further speculate on how the disjunction of E. arborea arose. The ancestor of E. arborea likely dispersed from Japan to North America where glaciation disrupted its distribution and speciation occurred. As glaciers retreated E. arborea likely dispersed into BC from warmer waters in the south and/or expanded from refugia off Vancouver Island and Haida Gwaii. While E. arborea is uncommon, our records extend its range into Alaska and Washington State. Along western Vancouver Island, BC, under warming conditions, E. arborea prevalence and abundance increased where once extirpated sea otters (Enhydra lutris) removed urchins. Where otters were absent, however, reduced summer wave heights, associated with warming, apparently allowed urchins to graze shallow-water kelps, which declined. We suggest that under warming conditions, sea otters may increase kelp resilience, with E. arborea becoming more prevalent in NE Pacific kelp forests. | H55: yes | I55: Haruka(Jonathan) | J55: no | K55: marine | L55: no | N55: This study covers the west coast of Canada | O55: Botanica marina | P55: 2021 | Q55: Watson, JC; Hawkes, MW; Lee, LC; Lamb, A | R55: 10.1515/bot-2021-0040
B56: E316 | C56: =LEFT(B56,1) & TEXT(RIGHT(B56,LEN(B56)-1),"0000") -> E0316 | D56: E0316 | E56: forest | F56: Climate change can reduce the risk of biological invasion by reducing propagule size | G56: Climate change has been conclusively linked to species extinctions, and to expansion and contractions and shifts of species ranges. Climate change is exerting similarly profound pressures on the individual stages of biological invasion which can significantly impact the biodiversity and ecology of invaded areas. Propagule pressure is perhaps the single most important determinant of invasion success, but the effects of climate change on propagule pressure are still largely uncertain because we have few observations of introduction events (or their size) that can be analyzed together with climate records. The common surrogate variables for propagule pressure do not logically respond to climate. Here I use a process-based simulation model to examine the potential effects of climate change (specifically temperature) on propagule size of a common invading insect species by estimating in-transit survivorship rate of propagules using historical and future (projected) temperatures and two common trade routes between a donor and a recipient location (Yokohama, Japan and Sydney, Australia). Propagule size (=the number of individuals in an introduction event) was lower under climate change temperatures than under historical temperatures in both routes. The route had significant effects on propagule size through its influence on the duration (and also the timing) of exposure to temperature conditions that are of time-sensitive importance to the development of the invasive species. Under historical temperatures propagule size was higher and less variable in the direct than the indirect route in 20 independent iterations. Under the future temperatures propagule size was also higher in the direct route but it was more variable than in the indirect route. Increased trade is increasing the opportunities for introductions, but the results reported here suggest that climate change will have inconsistent effects on biological invasion because of the complex relationship between temperature and insect ontogeny. | H56: yes | I56: Haruka(Jonathan) | J56: no | K56: unknown | L56: no | N56: This study analyze the impact of climate change on the risk of biological invasion | O56: Biological invasions | P56: 2017 | Q56: Gray, DR | R56: 10.1007/s10530-016-1291-2
B57: E319 | C57: =LEFT(B57,1) & TEXT(RIGHT(B57,LEN(B57)-1),"0000") -> E0319 | D57: E0319 | E57: forest | F57: Stable persistence of relict populations involved evolutionary shifts of reproductive characters in the genus tanakaea (saxifragaceae) | G57: Tertiary relicts often show evolutionary stasis in morphology and ecology and have been hypothesized to retain stable population sizes in refugia. However, recent studies have reported that some relicts evolutionarily shifted their physiology, ecology, and morphology and experienced various patterns of demography. To understand the historical survival of relict plants, a multidimensional study investigating the evolution of ecological and morphological traits as well as population demographic history is needed. The genus Tanakaea (Saxifragaceae) comprises two species in China and Japan. These species share most vegetative characteristics and are sometimes treated as a single species. The distribution pattern is relictual, as the populations are confined to small areas in mesic warm temperate forests less influenced by Quaternary glacial climates. Focusing on the relictual plant group, this study tested the hypotheses of evolutionary stasis and population stability in long-term refugia. Genetic analyses using plastome sequences and genome-wide single-nucleotide polymorphisms revealed divergence of the two species approximately 6.8 million years ago and strong genetic differentiation of the regional populations. Demographic analysis revealed that almost all populations retained stable population sizes during glacial-interglacial climate changes, supporting the traditional view. However, morphological assessments revealed a simultaneous shift in breeding systems (from hermaphrodite to dioecy/non-clonal to clonal reproduction) in Japanese species and intraspecific differentiation of leaf traits. Therefore, the relict species do not show evolutionary stasis in every aspect. Changes in reproductive characteristics may have contributed to their long-term in situ survival. | H57: yes | I57: Haruka(Jonathan) | J57: no | K57: terrestrial | L57: no | N57: the historical survival of relict plants, Ice age | O57: Journal of systematics and evolution | P57: 2022 | Q57: Takahashi, D; Isagi, Y; Li, P; Qiu, YX; Setoguchi, H; Suyama, Y; Matsuo, A; Tsunamoto, Y; Sakaguchi, S | R57: 10.1111/jse.12849
B58: E320 | C58: =LEFT(B58,1) & TEXT(RIGHT(B58,LEN(B58)-1),"0000") -> E0320 | D58: E0320 | E58: forest | F58: Combined modelling of distribution and niche in invasion biology:: a case study of two invasive tetramorium ant species | G58: Spatial modelling of species distributions has become an important tool in the study of biological invasions. Here, we examine the utility of combining distribution and ecological niche modelling for retrieving information on invasion processes, based on species occurrence data from native and introduced ranges. Specifically, we discuss questions, concerning (1) the global potential to spread to other ranges, (2) the potential to spread within established invasions, (3) the detectability of niche differences across ranges, and (4) the ability to infer invasion history through data from the introduced range. We apply this approach to two congeneric pavement ants, Tetramorium sp.E (formerly T. caespitum (Linnaeus 1758)) and T. tsushimae Emery 1925, both introduced to North America. We identify (1) the potential of both species to inhabit ranges worldwide, and (2) the potential of T. sp.E and T. tsushimae, to spread to 23 additional US states and to five provinces of Canada, and to 24 additional US states and to one province of Canada, respectively. We confirm that (3) niche modelling can be an effective tool to detect niche shifts, identifying an increased width of T. sp.E and a decreased width of T. tsushimae following introduction, with potential changes in niche position for both species. We make feasible that (4) combined modelling could become an auxiliary tool to reconstruct invasion history, hypothesizing admixture following multiple introductions in North America for T. sp.E, and a single introduction to North America from central Japan, for T. tsushimae. Combined modelling represents a rapid means to formulate testable explanatory hypotheses on invasion patterns and helps approach a standard in predictive invasion research. | H58: yes | I58: Haruka(Jonathan) | J58: no | K58: terrestrial | L58: no | N58: This study identifies the naitive niche and introduced niche of invasive species | O58: Diversity and distributions | P58: 2008 | Q58: Steiner, FM; Schlick-Steiner, BC; VanDerWal, J; Reuther, KD; Christian, E; Stauffer, C; Suarez, AV; Williams, SE; Crozier, RH | R58: 10.1111/j.1472-4642.2008.00472.x
B59: E321 | C59: =LEFT(B59,1) & TEXT(RIGHT(B59,LEN(B59)-1),"0000") -> E0321 | D59: E0321 | E59: forest | F59: Bird community heterogeneity along four gradients of different orientations on a temperate mountain | G59: Mountains harbour high biodiversity that is facing a crisis due to recent climate change. Bird communities shift along mountain gradients. Some previous studies have suggested that the effect of vegetation is prevalent on temperate mountains. In this study, we investigated the limiting effects of vegetation on the altitudinal distribution of birds on Mount Norikura in central Japan, by comparing bird communities along four gradients of different orientations. We recorded birds using the line-transect method and classified vegetation into six types: montane deciduous broadleaved forest, subalpine coniferous forest, subalpine birch forest, Japanese Stone Pine scrub forest, alpine tundra and bare ground below the alpine area. We identified the treelines and ecotones between the predominant vegetation types along each gradient. We found that bird species composition changed drastically at the treeline along three gradients. A non-metric multidimensional scaling (NMDS) ordination revealed: 1) the similarity between bird community structures in the subalpine coniferous forest and the Japanese Stone Pine scrub forest differed among the gradients, 2) despite birch being broadleaved, the bird community in the subalpine birch forest was a subset of that in the subalpine coniferous forest and was more similar to that in the subalpine coniferous forest than that in the montane deciduous broadleaved forest, and 3) in upper parts of the subalpine zone, the bird community structures in the subalpine coniferous and birch forests were similar to each other. Our findings suggest that although the treeline limits the distribution of forest-dwelling bird species, this effect differs among gradients with different orientations, probably depending on the scrub height of the Japanese Stone Pine scrub forests. Furthermore, the heterogeneity of coniferous and birch forests in the upper parts of the subalpine zone may have little effect on the altitudinal distribution of birds. | H59: yes | I59: Haruka(Jonathan) | J59: no | K59: alpine | L59: no | N59: This study elucidates changes in bird community composition as a result of elevation gradients. | O59: Ornithological science | P59: 2021 | Q59: Iijima, D; Morimoto, G | R59: 10.2326/osj.20.65
B60: E327 | C60: =LEFT(B60,1) & TEXT(RIGHT(B60,LEN(B60)-1),"0000") -> E0327 | D60: E0327 | E60: forest | F60: Plant molecular phenology and climate feedbacks mediated by BVOCs | G60: Climate change profoundly affects the timing of seasonal activities of organisms, known as phenology. The impact of climate change is not unidirectional; it is also influenced by plant phenology as plants modify atmospheric composition and climatic processes. One important aspect of this interaction is the emission of biogenic volatile organic compounds (BVOCs), which link the Earth's surface, atmosphere, and climate. BVOCemissions exhibit significant diurnal and seasonal variations and are therefore considered essential phenological traits. To understand the dynamic equilibrium arising from the interplay between plant phenology and climate, this review presents recent advances in comprehending the molecular mechanisms underpinning plant phenology and its interaction with climate. We provide an overview of studies investigating molecular phenology, genome-wide gene expression analyses conducted in natural environments, and how these studies revolutionize the concept of phenology, shifting it from observable traits to dynamic molecular responses driven by gene-environment interactions. We explain how this knowledge can be scaled up to encompass plant populations, regions, and even the globe by establishing connections between molecular phenology, changes in plant distribution, species composition, and climate. | H60: maybe | I60: Dai | J60: no | O60: Annual review of plant biology | P60: 2024 | Q60: Satake, A; Hagiwara, T; Nagano, AJ; Yamaguchi, N; Sekimoto, K; Shiojiri, K; Sudo, K | R60: 10.1146/annurev-arplant-060223-032108
B61: E338 | C61: =LEFT(B61,1) & TEXT(RIGHT(B61,LEN(B61)-1),"0000") -> E0338 | D61: E0338 | E61: forest | F61: Evidence for cryptic northern refugia in the last glacial period in cryptomeria japonica | G61: Background and Aims Distribution shifts and natural selection during past climatic changes are important factors in determining the genetic structure of forest species. In particular, climatic fluctuations during the Quaternary appear to have caused changes in the distribution ranges of plants, and thus strongly affected their genetic structure. This study was undertaken to identify the responses of the conifer Cryptomeria japonica, endemic to the Japanese Archipelago, to past climatic changes using a combination of phylogeography and species distribution modelling (SDM) methods. Specifically, this study focused on the locations of refugia during the last glacial maximum (LGM). Methods Genetic diversity and structure were examined using 20 microsatellite markers in 37 populations of C. japonica. The locations of glacial refugia were assessed using STRUCTURE analysis, and potential habitats under current and past climate conditions were predicted using SDM. The process of genetic divergence was also examined using the approximate Bayesian computation procedure (ABC) in DIY ABC to test the divergence time between the gene pools detected by the STRUCTURE analysis. Key Results STRUCTURE analysis identified four gene pools: northern Tohoku district; from Chubu to Chugoku district; from Tohoku to Shikoku district on the Pacific Ocean side of the Archipelago; and Yakushima Island. DIY ABC analysis indicated that the four gene pools diverged at the same time before the LGM. SDM also indicated potential northern cryptic refugia. Conclusions The combined evidence from microsatellites and SDM clearly indicates that climatic changes have shaped the genetic structure of C. japonica. The gene pool detected in northern Tohoku district is likely to have been established by cryptic northern refugia on the coast of the Japan Sea to the west of the Archipelago. The gene pool in Yakushima Island can probably be explained simply by long-term isolation from the other gene pools since the LGM. These results are supported by those of SDM and the predicted divergence time determined using ABC analysis. | H61: yes | I61: Dai | J61: yes | K61: Forest | L61: no | M61: Fig. 4 | O61: Annals of botany | P61: 2014 | Q61: Kimura, MK; Uchiyama, K; Nakao, K; Moriguchi, Y; San Jose-Maldia, L; Tsumura, Y | R61: 10.1093/aob/mcu197
B62: E352 | C62: =LEFT(B62,1) & TEXT(RIGHT(B62,LEN(B62)-1),"0000") -> E0352 | D62: E0352 | E62: forest | F62: Colliding fragment islands transport independent lineages of endemic rock-crawlers (grylloblattodea: grylloblattidae) in the japanese archipelago | G62: Fragment islands, viewed from the paradigm of island biogeographic theory, depend on continual immigration from continental sources to maintain levels of species diversity, or otherwise undergo a period of relaxation where species diversity declines to a lower equilibrium. Japan is a recently derived fragment island with a rich endemic flora and fauna. These endemic species have been described as paleoendemics, and conversely as recently derived Pleistocene colonists. Geological events in the Miocene period, notably the fragmentation and collision of islands, and the subsequent uplift of mountains in central Japan, provided opportunities for genetic isolation. More recently, cyclical climatic change during the Pliocene and Pleistocene periods led to intermittent land bridge connections to continental Asia. Here we investigate the pattern and timing of diversification in a diverse endemic lineage in order to test whether ongoing migration has sustained species diversity, whether there is evidence of relaxation, and how geological and climatic events are associated with lineage diversification. Using multi-locus genetic data, we test these hypotheses in a poorly dispersing, cold-adapted terrestrial insect lineage (Grylloblattodea: Grylloblattidae) sampled from Japan, Korea, and Russia. In phylogenetic analyses of concatenated data and a species tree approach, we find evidence of three deeply divergent lineages of rock-crawlers in Japan consistent with the pattern of island fragmentation from continental Asia. Tests of lineage diversification rates suggest that relaxation has not occurred and instead endemism has increased in the Japanese Grylloblattidae following mountain-building events in the Miocene. Although the importance of climate change in generating species diversity is a commonly held paradigm in Japanese biogeography, our analyses, including analyses of demographic change and phylogeographic range shifts in putative species, suggests that Pleistocene climatic change has had a limited effect on the diversification of rock-crawlers. | H62: yes | I62: Dai | J62: yes | K62: Forest | L62: no | M62: Fig. 5, A1 | O62: Molecular phylogenetics and evolution | P62: 2013 | Q62: Schoville, SD; Uchifune, T; Machida, R | R62: 10.1016/j.ympev.2012.11.022
B63: E355 | C63: =LEFT(B63,1) & TEXT(RIGHT(B63,LEN(B63)-1),"0000") -> E0355 | D63: E0355 | E63: forest | F63: The first fossils of the most basal pseudoscorpion family (arachnida: pseudoscorpiones: pseudotyrannochthoniidae): evidence for major biogeographical shifts in the european paleofauna | G63: Pseudoscorpions belong to the oldest terrestrial lineages with origins in the Devonian (ca. 385 Ma) but their fossil record is extremely sparse and little is known about their diversification over time. Here, we describe the first fossil species of the pseudoscorpion family Pseudotyrannochthoniidae that resemble the Devonian fossils in major details, such as the chaetotaxy of the pedipalps. We describe two new species, Allochthonius balticus sp. nov. from Baltic amber and Centrochthonius bitterfeldicus sp. nov. from Bitterfeld amber in northern Europe. Both species can unequivocally be assigned to extant genera and provide further evidence for dramatic range shifts in European invertebrate biota since the Paleogene. Allochthonius Chamberlin, 1929 is a diverse genus in eastern Asia (China, Korea, and Japan) today but does not occur anywhere in central Asia, Europe or North America. Centrochthonius Beier, 1931 is a poorly known genus but seems to be restricted to high altitude habitats in central Asia (China, Kyrgyzstan, and Nepal). With range retractions to regions more than 4600 km away from the European amber deposits, the fossils highlight total lineage extinction in Europe and survival in refugia that are climatically and botanically most similar to the Baltic amber forest of the Eocene. Overall, our results support the concept of morphological but potentially also ecological stasis in major pseudoscorpion lineages over long periods of time and agree with previous studies that suggested a warm temperate rather than subtropical or tropical climate for the time of amber deposition. | H63: yes | I63: Dai | J63: no | O63: Palz | P63: 2022 | Q63: Schwarze, D; Harms, D; Hammel, JU; Kotthoff, U | R63: 10.1007/s12542-021-00565-8
B64: E368 | C64: =LEFT(B64,1) & TEXT(RIGHT(B64,LEN(B64)-1),"0000") -> E0368 | D64: E0368 | E64: forest | F64: Effects of landscape and demographic history on genetic variation in picea glehnii at the regional scale | G64: To evaluate the effects of landscape and demographic history on genetic variation in Picea glehnii at a regional scale we have investigated the genetic diversity and genetic differentiation of P. glehnii populations in the Furano region, central Hokkaido, Japan, using seven simple sequence repeat (SSR) markers. We found significant correlations between elevation and genetic diversity parameters. The value of A ([46]) increased and the value of F (IS) decreased with increasing elevation, while F (IS) values were not significantly different from 0 in any of the populations. Significant recent bottlenecks were detected for isolated populations at low-elevation sites and for relatively large populations at moderate- and high-elevation sites. Evolutionary events pre-dating the Holocene should be taken into consideration, as elevational gradients should be with respect to locally adapted traits such as flowering phenology, However, the palynological data from the Holocene in this region suggest that the distribution pattern of genetic diversity of P. glehnii detected here may have been influenced by past demographic history related to the elevation shifts in this species' distribution associated with climate change during this period. Population differentiation was low, with F (ST) and G'(ST) values of 0.022 and 0.065, respectively. However, genetic boundaries were detected around one swamp population (C13). Therefore, significant isolation by distance (IBD) was not detected when all populations were considered, but there was significant IBD when the C13 population was excluded. Information on genetic diversity and genetic differentiation at the regional scale may be useful for selecting seed sources for afforestation programs for P. glehnii. | H64: yes | I64: Dai | J64: no | K64: Forest | L64: no | N64: Genetic pattern along elevation | O64: Ecological research | P64: 2009 | Q64: Goto, S; Tsuda, Y; Koike, Y; Lian, CL; Ide, Y | R64: 10.1007/s11284-009-0611-8
B65: E371 | C65: =LEFT(B65,1) & TEXT(RIGHT(B65,LEN(B65)-1),"0000") -> E0371 | D65: E0371 | E65: forest | F65: A new urban landscape in east-southeast asia, 2000-2010 | G65: East-Southeast Asia is currently one of the fastest urbanizing regions in the world, with countries such as China climbing from 20 to 50% urbanized in just a few decades. By 2050, these countries are projected to add 1 billion people, with 90% of that growth occurring in cities. This population shift parallels an equally astounding amount of built-up land expansion. However, spatially-and temporally-detailed information on regional-scale changes in urban land or population distribution do not exist; previous efforts have been either sample-based, focused on one country, or drawn conclusions from datasets with substantial temporal/spatial mismatch and variability in urban definitions. Using consistent methodology, satellite imagery and census data for >1000 agglomerations in the East-Southeast Asian region, we show that urban land increased >22% between 2000 and 2010 (from 155 000 to 189 000 km(2)), an amount equivalent to the area of Taiwan, while urban populations climbed >31% (from 738 to 969 million). Although urban land expanded at unprecedented rates, urban populations grew more rapidly, resulting in increasing densities for the majority of urban agglomerations, including those in both more developed (Japan, South Korea) and industrializing nations (China, Vietnam, Indonesia). This result contrasts previous sample-based studies, which conclude that cities are universally declining in density. The patterns and rates of change uncovered by these datasets provide a unique record of the massive urban transition currently underway in East-Southeast Asia that is impacting local-regional climate, pollution levels, water quality/availability, arable land, as well as the livelihoods and vulnerability of populations in the region. | H65: yes | I65: Dai | J65: no | N65: Human shifts indexed by the expantion of cities? | O65: Environmental research letters | P65: 2015 | Q65: Schneider, A; Mertes, CM; Tatem, AJ; Tan, B; Sulla-Menashe, D; Graves, SJ; Patel, NN; Horton, JA; Gaughan, AE; Rollo, JT; Schelly, IH; Stevens, FR; Dastur, A | R65: 10.1088/1748-9326/10/3/034002
B66: E376 | C66: =LEFT(B66,1) & TEXT(RIGHT(B66,LEN(B66)-1),"0000") -> E0376 | D66: E0376 | E66: forest | F66: Expanding global commodities trade and consumption place the world's primates at risk of extinction | G66: As a consequence of recent human activities. populations of approximately 75% of the world's primates are in decline, and more than 60% of species (n = 512) are threatened with extinction. Major anthropogenic pressures on primate persistence include the widespread loss and degradation of natural habitats caused by the expansion of industrial agriculture, pastureland for cattle, logging, mining, and fossil fuel extraction. This is the result of growing global market demands for agricultural and nonagricultural commodities. Here, we profile the effects of international trade of forest-risk agricultural and nonagricultural commodities, namely soybean, oil palm, natural rubber, beef, forestry products, fossil fuels, metals, minerals, and gemstones on habitat conversion in the Neotropics, Africa, and South and Southeast Asia. Total estimated forest loss for these regions between 2001 and 2017 was ca 179 million ha. The average percent of commodity-driven permanent deforestation for the period 2001-2015 was highest in Southeast Asia (47%) followed by the Neotropics (26%), South Asia (26%), and Africa (7%). Commodities exports increased significantly between 2000 and 2016 in all primate range regions leading to the widespread conversion of forested land to agricultural fields and an increase in natural resource extraction. In 2016, US $1.1 trillion of natural-resource commodities were traded by countries in primate range regions. The Neotropics accounted for 41% of the total value of these exports, Southeast Asia for 27%, Africa 21%, and South Asia 11%. Major commodity exporters in 2016 were Brazil, India, Indonesia, Malaysia an d South Africa, countries of high primate diversity and endemism. Among the top 10 importers were China, the US, Japan, and Switzerland. Primate range countries lag far behind importer nations in food security and gross domestic product per capita, suggesting that trade and commodity-driven land-use have done little to generate wealth and well-being in primate habitat countries. Modeling of land-use and projected extinction of primate species by 2050 and 2100 under a business as usual scenario for 61 primate range countries indicate that each country is expected to see a significant increase in the number of species threatened with extinction. To mitigate this impending crisis, we advocate the greening of trade, a global shift toward a low-meat diet, reduced consumption of oil seed, diminished use of tropical timber, fossil fuels, metals, minerals, and gemstones from the tropics, accompanied by a stronger and sustained global resolve to regulate and reverse the negative impacts of growing unsustainable global demands and commodity trade on income inequality, and the destruction of primates and their habitats. | H66: yes | I66: Dai | J66: no | O66: Peerj | P66: 2019 | Q66: Estrada, A; Garber, PA; Chaudhary, A | R66: 10.7717/peerj.7068
B67: E390 | C67: =LEFT(B67,1) & TEXT(RIGHT(B67,LEN(B67)-1),"0000") -> E0390 | D67: E0390 | E67: forest | F67: Phylogeography of the endangered orchids cypripedium japonicum and cypripedium formosanum in east asia: deep divergence at infra- and interspecific levels | G67: To date, little is known about the past evolutionary trajectories of rare and endangered orchids native to mainland China, Japan, and Korea (the CJK region). In this study, we focus on two endangered orchids, Cypripedium japonicum (present in the three countries) and C. formosanum (endemic to Taiwan), to understand the divergence/speciation models that would have been operating in this group, including genetic diversity, geographic structure, and colonization pathways across the region. Using a combination of five cpDNA regions, we reconstructed phylogenetic trees and investigated the genetic diversity/structure of 20 populations. Ecological niche modeling was used to gain insight into the paleodistribution and dispersal corridors at the Last Glacial Maximum and to survey climatic niche differences. Populations from mainland China + Korea, Japan, and Taiwan formed three distinct monophyletic lineages and were placed into separate genetic clusters, agreeing with geographic barriers and species boundaries. Populations of C. japonicum in mainland China harbored the highest diversity, suggesting the presence of multiple glacial refugia. The Korean populations would have originated from either western/central or eastern China, probably using a dispersal corridor across the East China Sea shelf. The divergence of C. formosanum is proposed under an allopatric speciation model, also highly influenced by a climate niche shift. In the context of previous studies, a deep divergence in cpDNA sequences between Chinese + Korean and Japanese populations of C. japonicum may be taken as an example of the speciation events of the CJK flora since the late Neogene that have led to its current species richness. | H67: yes | I67: Dai | J67: yes | K67: Forest | L67: no | M67: Fig.5, | N67: Past to present potential distribution map. | O67: Taxon | P67: 2022 | Q67: Han, LX; Jin, Y; Zhang, JL; Li, XL; Chung, MY; Herrando-Moraira, S; Kawahara, T; Yukawa, T; Chung, SW; Chung, JM; Kim, YD; López-Pujol, J; Chung, MG; Tian, HZ | R67: 10.1002/tax.12710
B68: E399 | C68: =LEFT(B68,1) & TEXT(RIGHT(B68,LEN(B68)-1),"0000") -> E0399 | D68: E0399 | E68: forest | F68: Wave-sheltered embayments are recruitment hotspots for tropical fishes on temperate reefs | G68: Poleward redistribution of species, facilitated by global warming, will be compromised if habitats at higher latitudes do not support the species' early life stages. For tropical reef fishes, reef structure may mediate colonisation of temperate regions; however, an understanding of key habitat requirements for colonisation is currently lacking. We show that density, diversity (taxonomic and trophic) and species richness of newly recruited tropical reef fishes were greater in embayed than exposed reefs in 2 mid-latitude temperate zones, where coastal waters are rapidly warming: southeastern Australia (30.5-33 degrees S) and western Japan (32-33.5 degrees N). Dietary generalists (e.g. planktivores and herbivores) and specialists (corallivores) associated more commonly with embayed reefs. Wave exposure was a stronger predictor of the density and richness of dietary generalists than water temperature, latitude, predatory fish densities, reef rugosities, benthos and distance to river mouths. Corallivores were strongly associated with branching corals, which were exclusive to highly sheltered reefs. We also explored habitat associations of 7 focal species within a coral reef, One Tree Island (OTI), Great Barrier Reef. Four species associated with wave sheltered over exposed reef on OTI and temperate Australian reef. However, Abudefduf vaigiensis, Pomacentrus coelestis and Acanthurus triostegus associated more with wave-sheltered reef in temperate regions. We hypothesise that cool temperate waters promote greater sheltering of some warm-adapted, tropical fishes by impacting their swimming/physiological performance. Results suggest availability of embayed temperate reefs may influence where some tropical fishes colonise with warming waters, through impacting recruitment. Wave exposure of reefs should be considered when predicting geographic responses of tropical fishes to climate change. | H68: yes | I68: Dai | J68: no | K68: Marine | L68: no | O68: Marine ecology progress series | P68: 2016 | Q68: Beck, HJ; Feary, DA; Nakamura, Y; Booth, DJ | R68: 10.3354/meps11599
B69: E400 | C69: =LEFT(B69,1) & TEXT(RIGHT(B69,LEN(B69)-1),"0000") -> E0400 | D69: E0400 | E69: forest | F69: Some like it hot! Rapid climate change promotes changes in distribution ranges of nezara viridula and nezara antennata in japan | G69: We compared past and current limits of the distribution range of the southern green stink bug, Nezara viridula (L.) (Heteroptera: Pentatomidae), in central Japan. In the early 1960s, the northern limit of the range was in Wakayama Prefecture and was limited by a +5 degrees C isothermal line for the mean January temperature. In 2006-2007, a new survey demonstrated that this northern limit had shifted northwards by 85 km (i.e., at a mean rate of 19.0 km per decade). The shift was most likely promoted by milder winter conditions. The mean January to February temperature in the region was 1.03-1.91 degrees C higher in 1998-2007 than in 1960-1969. The number of cold days (with the mean temperature below +5 degrees C) also significantly decreased, while the annual lowest temperature significantly increased. Nezara viridula was found mostly close to those locations where (i) the mean January temperature exceeded +5 degrees C, (ii) the mean number of cold days did not exceed 26 in January to February, and (iii) where the mean annual lowest temperature did not drop below -3.0 degrees C. The general linear model shows that the mean January temperature and number of cold days are the most important factors controlling the northern limit of distribution of N. viridula. All the climatic data suggest that over the last 45 years, environmental conditions have become more favourable for overwintering of N. viridula at many locations in central Japan. This has probably promoted the northward spread of the species, representing a direct response to climate warming. A sympatrically distributed congeneric, Nezara antennata Scott, seems to respond to the warming by a retreat from the ocean coast towards cooler elevated habitats, which might be a complex response to elevated temperature and interspecific mating with N. viridula. It is suggested that the range changes in both species will continue in response to further climate change. | H69: yes | I69: Dai | J69: yes | K69: Forest, Grassland | L69: yes | M69: Abstract, Fig. 2 | N69: Distribution shift at the northern edge | O69: Entomologia experimentalis et applicata | P69: 2009 | Q69: Tougou, D; Musolin, DL; Fujisaki, K | R69: 10.1111/j.1570-7458.2008.00818.x
B70: E402 | C70: =LEFT(B70,1) & TEXT(RIGHT(B70,LEN(B70)-1),"0000") -> E0402 | D70: E0402 | E70: forest | F70: Climate-driven range shifts of brown seaweed sargassum horneri in the northwest pacific | G70: Climate-driven shifts of coastal species' ranges constitute a key factor shaping both the vegetation composition and biodiversity of coastal ecosystems. Although phylogeographic studies relying on genetic data have shed light on the evolutionary history of macroalgae along the Northwest Pacific (NW-Pacific) coast, their distribution dynamics are less understood and require interdisciplinary examination. Here, we used a combination of species distribution models (SDMs) and genetic data to explain the causes of population persistence and genetic differentiation and their consequences for the brown seaweed Sargassum horneri in the NW-Pacific. In this region, the phylogeographic structure of S. homeri was analyzed by screening 72 populations spawning across the entire coastal distribution and obtaining their mtDNA cox3 data. Population genetic structure and SDMs based on paleoclimatic data consistently revealed that southern coasts of the Sea of Japan, North-Pacific-Japan, and the northern part of Okinawa Trough might have served as potential refugia for S. horneri during the Last Glacial Maximum (LGM). Furthermore, we projected the distribution dynamics of S. horneri under future climate scenarios. The range of S. homeri was predicted to move northward, with a significant loss of suitable habitat, under the high emissions scenario (RCP 8.5). By contrast, projected range shifts were minimal under the low emissions scenario (RCP 2.6). Furthermore, North-Pacific-Japan was projected to be long-term persistence habitat for S. horneri under future climatic conditions, thus including this area in conservation planning could help mitigate for climate change implications. Our results enable a better understanding of the impacts of climate change on the spatio-temporal distribution of macroalgae and how this can inform coastal management and marine conservation planning. | H70: yes | I70: Dai | J70: yes | K70: Marine | L70: no | M70: Fig. 1, 2, 4 | O70: Frontiers in marine science | P70: 2020 | Q70: Li, JJ; Huang, SH; Liu, ZY; Bi, YX | R70: 10.3389/fmars.2020.570881
B71: E406 | C71: =LEFT(B71,1) & TEXT(RIGHT(B71,LEN(B71)-1),"0000") -> E0406 | D71: E0406 | E71: forest | F71: Bottom temperature warming and its impact on demersal fish off the pacific coast of northeastern japan | G71: Global climate change occurs not only at the ocean surface but also at the ocean bottom, which is the main habitat of demersal fish. To clarify the current status of bottom temperature warming off the Pacific coast of northeastern Japan, we examined gridded bottom temperature fields from 2003 to 2019. These fields were created by a newly developed gridding method using flexible Gaussian filter weighting with time, distance, and depth. Spatially averaged bottom temperature had a strong, significant warming trend of 0.083 to 0.115 degrees C yr(-1) in depth zones of 150-300 m, indicating bottom temperature warming. Corresponding to the warming, increases in landing amounts were found for warm-water species such as searobin in the middle region of our study area (37 degrees 50'-39 degrees N). Seasonal catch amounts suggest that ribbon fish and swimming crab recently began to overwinter and reproduce in the area. The distribution shifts of non-target species in fisheries were also analyzed using bottom otter trawl survey data from the area from 2003 to 2019. Northward distribution shifts and increases in density were observed in blackbelly lantern shark and bighand grenadier, indicating that bottom temperature warming led to habitat expansion. Conversely, darkfin sculpin and jelly eelpout shifted northward with decreasing density, suggesting that bottom temperature warming had a negative effect on them. Deepsea bone-fish shifted deeper into colder waters with increasing density and mean body weight. Thus, changes and responses of demersal fish to bottom temperature warming in the area were revealed. | H71: yes | I71: Dai | J71: yes | K71: Marine | L71: yes | M71: Fig. 5, 6, 7, 8, 9 | O71: Marine ecology progress series | P71: 2021 | Q71: Kakehi, S; Narimatsu, Y; Okamura, Y; Yagura, A; Ito, S | R71: 10.3354/meps13852
B72: E407 | C72: =LEFT(B72,1) & TEXT(RIGHT(B72,LEN(B72)-1),"0000") -> E0407 | D72: E0407 | E72: forest | F72: Area-specific temporal changes of species composition and species-specific range shifts in rocky-shore mollusks associated with warming kuroshio current | G72: Increases of low-latitude species in various sea areas and poleward shifts of ranges of many species have been reported and linked to warming environments. To examine the generality of these trends for mollusks, we conducted 7 quadrat surveys during 1978-2006 on Pacific rocky shores in Japan (26.6-45.0A degrees N). Results showed that the dominance of southern species increased on 11 of the 15 shores in a southern, warming sea area but on only 1 of the 6 shores in a northern area with no warming trend. The latitudes of species ranges increased on average but showed large interspecific variations which showed a weak, positive correlation with interspecific taxonomic distance. The differences of these results from the previously reported trends are discussed in relation to the unique current patterns in our study area and the phylogenetic constraints of species-specific responses to a warming environment. | H72: yes | I72: Dai | J72: yes | K72: Marine | L72: yes | M72: Fig. 3, 5, 6, ESM4 | O72: Marine biology | P72: 2011 | Q72: Kurihara, T; Takami, H; Kosuge, T; Chiba, S; Iseda, M; Sasaki, T | R72: 10.1007/s00227-011-1717-4
B73: E409 | C73: =LEFT(B73,1) & TEXT(RIGHT(B73,LEN(B73)-1),"0000") -> E0409 | D73: E0409 | E73: forest | F73: Investigating effect of climate warming on the population declines of sympetrum frequens during the 1990s in three regions in japan | G73: Climate warming is of concern as a key factor in the worldwide decline in insect populations. In Japan, numbers of a common dragonfly in rice paddy fields, Sympetrum frequens, decreased sharply in the 1990s. Because S. frequens migrates to cooler mountains in summer, climate warming has been suggested as one of the main causes of the population decline in addition to agronomic factors. Here, we analysed the relation between summer temperatures and population densities of S. frequens and the related S. infuscatum, which does not migrate to mountains in summer, using published population monitoring data and temperature data from three regions (Toyama, Ishikawa, and Shizuoka) in Japan. Decadal differences in summer temperatures lay within the range of fluctuations among years, suggesting that an increase in summer temperatures cannot explain the past sharp population declines. However, regression analyses using monitoring data from Toyama showed that the population dynamics of both species in autumn are negatively correlated with summer temperatures in the same year. These results suggest that high temperatures in summer directly affect adult mortality to an extent that results in a decrease in population growth. | H73: yes | I73: Dai | J73: no | K73: Forest, Grassland | L73: no | O73: Scientific reports | P73: 2020 | Q73: Nakanishi, K; Koide, D; Yokomizo, H; Kadoya, T; Hayashi, T | R73: 10.1038/s41598-020-69532-8
B74: E410 | C74: =LEFT(B74,1) & TEXT(RIGHT(B74,LEN(B74)-1),"0000") -> E0410 | D74: E0410 | E74: forest | F74: Advancing timberline on mt. Fuji between 1978 and 2018 | G74: Climate change is a major cause of changes in alpine and polar vegetation, particularly at the edges of distributions. In temperate regions, these changes are expected to occur at the timberline of alpine zones. On Mt. Fuji, the highest mountain in Japan, the timberline is located 2400-2500 m above sea level. Over a 40-year period (1978-2018), we researched changes in the timberline vegetation of Mt. Fuji. A permanent belt transect extending from the upper timberline to subalpine zones was set up in August 1978. Tree diameters and heights were recorded at the establishment of the transect and every 20 years afterwards. Over the 40 years of the study, the timberline advanced rapidly upwards, and the degree of vegetation cover above the timberline increased remarkably. Notably, the expansion of Salix reinii into the upper part of the timberline facilitated the subsequent spread of Larix kaempferi into this zone. Seedlings of L. kaempferi were particularly abundant at the upper timberline and became established on the uppermost part of the slope. The shape of L. kaempferi at the upper timberline changed from a prostrate form to an upright tree form. We conclude that the upward advance of the alpine timberline observed on Mt. Fuji is due to climate change. | H74: yes | I74: Dai | J74: no | K74: Alpine | L74: no | O74: Plants | P74: 2020 | Q74: Sakio, H; Masuzawa, T | R74: 10.3390/plants9111537
B75: E411 | C75: =LEFT(B75,1) & TEXT(RIGHT(B75,LEN(B75)-1),"0000") -> E0411 | D75: E0411 | E75: forest | F75: Effects of wind and thermal conditions on timberline formation in central japan: a lattice model | G75: The upper distribution limit of tall tree species Abies mariesii is the timberline in central Japan, and dwarf pine Pinus pumila dominates above the timberline to near the summit. My previous studies suggested that the main cause of the timberline formation is the increase in mortality due to strong wind in winter rather than low growth due to low summer temperature. This study evaluated how wind velocity affects timberline formation and if the altitude of timberline moves upward due to high thermal conditions, by using a lattice model. Increase in wind velocity throughout the altitude lowered the altitudes of upper distribution limits of the two species. On the contrary, prolonged growth period due to high thermal conditions increased the upper distribution limit of P. pumila, and the upper distribution limit of A. mariesii was hardly affected by the change of growth period. However, the upward shift of the upper distribution limit of P. pumila due to the prolonged growth period in the model would not be realistic because P. pumila had already distributed up to near the summit. This study concludes that A. mariesii is a superior competitor to P. pumila at low altitudes with low wind velocity, but dwarf pine P. pumila can dominate at higher altitudes because A. mariesii suffers severe mechanical damage due to strong wind in winter, and that the altitude of the timberline does not move upward even under high thermal conditions due to global warming. | H75: yes | I75: Dai | J75: no | K75: Alpine | L75: no | N75: Model simulation | O75: Ecological research | P75: 2014 | Q75: Takahashi, K | R75: 10.1007/s11284-014-1129-2
B76: E414 | C76: =LEFT(B76,1) & TEXT(RIGHT(B76,LEN(B76)-1),"0000") -> E0414 | D76: E0414 | E76: forest | F76: Quaternary range-shift history of japanese wingnut (pterocarya rhoifolia) in the japanese archipelago evidenced from chloroplast dna and ecological niche modeling | G76: Based on organelle DNA phylogeographic analyses and ecological niche modeling (ENM), we investigated the range-shift history of the Japanese wingnut (Pterocarya rhoifolia) during the Quaternary climatic oscillations with particular emphasis on the Last Glacial Maximum (LGM). Phylogeographic patterns of this species were determined using 376 individuals from 53 populations for chloroplast DNA sequencing of three spacers. Spatial analysis of molecular variance revealed that the current phylogeographic structure would be sculptured by multiple range shifts from each glacial refugium, which would have been repeated several times during the Quaternary climatic oscillations. High haplotype diversity and private haplotypes were detected in southwestern Japan, where wingnut is currently infrequent and found mainly in high mountains, whereas in northernmost Japan, haplotype diversity was low though this plant is quite common at present. According to ENM approach, during the LGM, the climatically suitable distribution areas were not recovered in northeastern Japan but in lowlands of southwestern Japan. Our combined results suggest that Japanese wingnut primarily persisted in the lowlands of southwestern Japan and coastlines below 36.5°N latitude during the LGM, having led to the postglacial range expansion from the refugia in each area of southwestern and lower latitudinal northeastern Japan, and to the wide-range recolonization from the southerly refugium/refugia to the north in northernmost Japan. The southwestern and coastal refugia have played a role in shaping the current haplotype diversity and phylogeographic structure, whereas some rear edge populations, harboring unique haplotypes, have been also maintained. | H76: yes | I76: Dai | J76: yes | K76: Forest | L76: no | M76: Fig. 4 | O76: Journal of Forest Research | P76: 2017 | Q76: K Sugahara, Y Kaneko, S Sakaguchi, S Ito, K Yamanaka, H Sakio, K Hoshizaki, W Suzuki, N Yamanaka, Y Isagi, A Momohara, H Setoguchi | R76: 10.1080/13416979.2017.1351837
B77: E416 | C77: =LEFT(B77,1) & TEXT(RIGHT(B77,LEN(B77)-1),"0000") -> E0416 | D77: E0416 | E77: forest | F77: Distribution range shift of two allied species, nezara viridula and n. antennata (hemiptera: pentatomidae), in japan, possibly due to global warming | G77: Intensive and successive field surveys on the relative abundance of Nezara viridula (Hemiptera: Pentatomidae) and N. antennata at various localities in northern Kyushu, Japan, together with scattered collection records of N. viridula in Kyushu and Honshu, clearly showed that N. viridula has been expanding its range northward since the 1960s. The present range of N. viridula in Kyushu coincided well with the areas where the mean temperature of the coldest month exceeds 5°C that has been suggested to be the lowest thermal limit for N. viridula to overwinter successfully. The future range of N. viridula is predicted to cover a large area of Kyushu if the temperature rises by 1.4 to 5.8°C by 2100. In some places, N. antennata seemed to have been replaced by N. viridula as a result of their interspecific mating that prevented N. antennata from intraspecific mating. This is because N. antennata was overwhelmed, in abundance, by N. viridula, which has a higher reproductive potential than N. antennata under warm conditions with a sufficient amount of food resources. Conversely, N. antennata populations recovered in a few places where N. viridula had replaced N. antennata in the 1950s, probably due to the shortage of rice plants on which N. viridula preferably reproduces. | H77: yes | I77: Dai | J77: yes | K77: Forest, Grassland | L77: no | M77: Fig. 5 | O77: Applied entomology and zoology | P77: 2007 | Q77: J Yukawa, K Kiritani, N Gyoutoku, N Uechi, D Yamaguchi, S Kamitani | R77: 10.1303/aez.2007.205
B78: E420 | C78: =LEFT(B78,1) & TEXT(RIGHT(B78,LEN(B78)-1),"0000") -> E0420 | D78: E0420 | E78: forest | F78: Distributional response of the rare and endangered tree species abies chensiensis to climate change in east asia | G78: Globally, increasing temperatures due to climate change have severely affected natural ecosystems in several regions of the world; however, the impact on the alpine plant may be particularly profound, further raising the risk of extinction for rare and endangered alpine plants. To identify how alpine species have responded to past climate change and to predict the potential geographic distribution of species under future climate change, we investigated the distribution records of A. chensiensis, an endangered alpine plant in the Qinling Mountains listed in the Red List. In this study, the optimized MaxEnt model was used to analyse the key environmental variables related to the distribution of A. chensiensis based on 93 wild distribution records and six environmental variables. The potential distribution areas of A. chensiensis in the last interglacial (LIG), the last glacial maximum (LGM), the current period, and the 2050s and 2070s were simulated. Our results showed that temperature is critical to the distribution of A. chensiensis, with the mean temperature of the coldest quarter being the most important climatic factor affecting the distribution of this species. In addition, ecological niche modeling analysis showed that the A. chensiensis distribution area in the last interglacial experiencing population expansion and, during the last glacial maximum occurring, a population contraction. Under the emission scenarios in the 2050s and 2070s, the suitable distribution area would contract significantly, and the migration routes of the centroids tended to migrate toward the southern high-altitude mountains, suggesting a strong response from the A. chensiensis distribution to climate change. Collectively, the results of this study provide a comprehensive and multidimensional perspective on the geographic distribution pattern and history of population dynamics for the endemic, rare, and endangered species, A. chensiensis, and it underscores the significant impact of geological and climatic changes on the geographic pattern of alpine species populations. | H78: maybe | I78: Dai | J78: no | K78: Forest | L78: no | N78: China | O78: Biology | P78: 2022 | Q78: Dong, P.B., Wang, L.Y., Wang, L.J., Jia, Y., Li, Z.H., Bai, G., Zhao, R.M., Liang, W., Wang, H.Y., Guo, F.X. and Chen, Y. | R78: 10.3390/biology11111659
B79: E421 | C79: =LEFT(B79,1) & TEXT(RIGHT(B79,LEN(B79)-1),"0000") -> E0421 | D79: E0421 | E79: forest | F79: Climate and historical factors controlling horizontal and vertical distribution patterns of two sympatric beech species, fagus crenata blume and fagus japonica maxim., in eastern japan | G79: The Japanese Archipelago is unique when viewed in terms of beech flora, since two native species, Fagus crenata Blume and Fagus japonica Maxim., occur sympatrically there. In order to examine the most important environmental or historical factors restricting the geographical ranges of these beech species in eastern Japan (34–44°N and 137–143°E), horizontal and vertical distributions were comparatively examined in detail. The study used two kinds of data sets: (1) DS1, constructed by assembling data from literature, herbarium specimens, etc., and (2) DS2, based on a mesh vegetation database. The upper range limit was expected to be in equilibrium with the current climatic conditions for both species (correlated with temperature factors for F. crenata and with snow depth for F. japonica). The lower range limit was also expected to be in equilibrium with the present climatic condition for both species, but the importance of competition with evergreen trees was also suggested. Dispersal limitation and a topo-geological barrier (for F. japonica) were expected to strongly restrict the northern range limit. Under contrasting climatic conditions in winter (between the Pacific and the Sea of Japan sides in eastern Japan) the geographic ranges of the two beech species are differentiated because of a difference in tolerance to heavy snowfall. A range shift model that assumes a migration lag along a horizontal direction because of dispersal limitation can explain the observed distribution patterns of these beech species in relation to climatic change in the Quaternary. | H79: yes | I79: Dai | J79: no | K79: Forest | L79: no | O79: Flora-morphology, distribution, functional ecology of plants | P79: 2010 | Q79: M Hara | R79: 10.1016/j.flora.2009.01.003
B80: E422 | C80: =LEFT(B80,1) & TEXT(RIGHT(B80,LEN(B80)-1),"0000") -> E0422 | D80: E0422 | E80: forest | F80: Range-expanding wildlife: modelling the distribution of large mammals in japan, with management implications | G80: The spatial distribution of large mammals has been increasing in industrial nations, often leading to conflicts with humans and significant alteration of natural ecosystems. Species distribution models (SDMs) of the sika deer, Japanese serow, wild boar, Japanese macaque and Asiatic black bear in Japan were constructed to identify the important factors for habitat management. We also projected two scenarios of their future range expansions under a scenario of no change in the variables, and one where the variables change according to a time series. Modelling showed that all species preferred forest and forest/agricultural ecotones. In the best models of the sika deer and wild boar, grasslands (GRASSs) were an important positive factor, while human population density and hunting pressures were negative factors. High human population density was also a negative factor with the Japanese serow and Asiatic black bear. Key environments for the distribution and expansion of large mammals were agricultural areas near forest and GRASSs. Therefore, limiting the access of large mammals to such habitats may contribute to wildlife management. In both scenarios, our projections suggest that the distributions of all species could expand by 2028, resulting in more conflict with humans and significant alterations to natural ecosystems in the future. In order to stop this damaging expansion, habitat management and landscape redesign are important. However, a SDM and future projection include uncertainty. It is necessary to validate the estimates and projections by monitoring the future changes in distribution. | H80: yes | I80: Dai | J80: no | K80: Forest | L80: no | N80: Future potential shifts for animals | O80: International journal of Geographical Information Science | P80: 2016 | Q80: MU Saito, H Momose, S Inoue, O Kurashima, H Matsuda | R80: 10.1080/13658816.2014.952301
B81: E424 | C81: =LEFT(B81,1) & TEXT(RIGHT(B81,LEN(B81)-1),"0000") -> E0424 | D81: E0424 | E81: forest | F81: Range shift and introgression of the rear and leading populations in two ecologically distinct rubusspecies | G81: The margins of a species’ range might be located at the margins of a species’ niche, and in such cases, can be highly vulnerable to climate changes. They, however, may also undergo significant evolutionary changes due to drastic population dynamics in response to climate changes, which may increase the chances of isolation and contact among species. Such species interactions induced by climate changes could then regulate or facilitate further responses to climatic changes. We hypothesized that climate changes lead to species contacts and subsequent genetic exchanges due to differences in population dynamics at the species boundaries. We sampled two closely related Rubus species, one temperate (Rubus palmatus) and the other subtropical (R. grayanus) near their joint species boundaries in southern Japan. Coalescent analysis, based on molecular data and ecological niche modelling during the Last Glacial Maximum (LGM), were used to infer past population dynamics. At the contact zones on Yakushima (Yaku Island), where the two species are parapatrically distributed, we tested hybridization along altitudinal gradients. Coalescent analysis suggested that the southernmost populations of R. palmatus predated the LGM (~20,000 ya). Conversely, populations at the current northern limit of R. grayanus diverged relatively recently and likely represent young outposts of a northbound range shift. These population dynamics were partly supported by the ensemble forecasting of six different species distribution models. Both past and ongoing hybridizations were detected near and on Yakushima. Backcrosses and advanced-generation hybrids likely generated the clinal hybrid zones along altitudinal gradients on the island where the two species are currently parapatrically distributed. Climate oscillations during the Quaternary Period and the response of a species in range shifts likely led to repeated contacts with the gene pools of ecologically distinct relatives. Such species interactions, induced by climate changes, may bring new genetic material to the marginal populations where species tend to experience more extreme climatic conditions at the margins of the species distribution. | H81: yes | I81: Dai | J81: yes | K81: Forest | L81: no | M81: Fig. 5 | O81: Bmc evolutionary biology | P81: 2014 | Q81: M Mimura, M Mishima, M Lascoux, T Yahara | R81: 10.1186/s12862-014-0209-9
B82: E426 | C82: =LEFT(B82,1) & TEXT(RIGHT(B82,LEN(B82)-1),"0000") -> E0426 | D82: E0426 | E82: forest | F82: Breeding range shift of the red-crowned crane (grus japonensis) under climate change | G82: The red-crowned crane (Grus japonensis) is an endangered species listed by International Union for Conservation of Nature (IUCN) HARRIS J (2013). The largest population of this species is distributed mainly in China and Russia, which is called continental population SU L (2012)–Curt D (1996). This population is migratory, which migrates from its breeding range located in Northeast China and Southern Russia, to the wintering range in the south of China to spend the winter every year. The breeding range of this species is critical for red-crowned crane to survive and maintain its population. Previous studies showed the negative effects of habitat loss and degradation on the breeding area of red-crowned crane Ma Z (1998), Claire M (2019). Climate change may also threat the survival of this endangered species. Previous studies investigated the impacts of climate change on the breeding range or wintering range in China Wu (2012), [1]. However, no study was conducted to assess the potential impacts of climate change on the whole breeding range of this species. Here, we used bioclimatic niche modeling to predict the potential breeding range of red-crowned crane under current climate conditions and project onto future climate change scenarios. Our results show that the breeding range of the continental population of red-crowned crane will shift northward over this century and lose almost all of its current actual breeding range. The climate change will also change the country owning the largest portion of breeding range from China to Russia, suggesting that Russia should take more responsibility to preserve this endangered species in the future. | H82: maybe | I82: Dai | J82: no | K82: Forest, Grassland | L82: no | N82: Future potential shifts for animals in Russia, China, and Mongolia | O82: Plos one | P82: 2020 | Q82: L Liu, J Liao, Y Wu, Y Zhang | R82: 10.1371/journal.pone.0229984
B83: E434 | C83: =LEFT(B83,1) & TEXT(RIGHT(B83,LEN(B83)-1),"0000") -> E0434 | D83: E0434 | E83: forest | F83: The role of microclimate in maintaining species distribution under climate change: a case study of the northern pika | G83: No abstract available | H83: maybe | I83: Dai | J83: yes | K83: Alpine | L83: yes | M83: Fig. 3-2, S5-1, Main text | O83: PhD dissertation | P83: 2024 | Q83: T Sakiyama | R83: https://eprints.lib.hokudai.ac.jp/dspace/bitstream/2115/94024/1/SAKIYAMA_Tomoki.pdf
B84: E439 | C84: =LEFT(B84,1) & TEXT(RIGHT(B84,LEN(B84)-1),"0000") -> E0439 | D84: E0439 | E84: forest | F84: Underlying geology and climate interactively shape climate change refugia in mountain streams | G84: Identifying climate‐change refugia is a key adaptation strategy for reducing global warming impacts. Knowledge of the effects of underlying geology on thermal regime along climate gradients and the ecological responses to the geology‐controlled thermal regime is essential to plan appropriate climate adaptation strategies. In the present study, the dominance of volcanic rocks in the watershed is used as a landscape‐scale surrogate for cold groundwater inputs to clarify the importance of underlying geology in stream ecosystems along climate gradients. First, using hundreds of monitoring stations distributed across multiple catchments, we explored the relationship between watershed geology and the mean summer water temperature of mountain streams along climate gradients in the Japanese archipelago. Mean summer water temperature was explained by the interaction between the watershed geology and climate in addition to independent effects. The cooling effect supported by volcanic rocks reached up to 3.3°C among study regions, which was more pronounced in streams with less summer precipitation or lower air temperatures. Next, we examined the function of volcanic streams as cold refugia under contemporary and future climatic conditions. Community composition analyses revealed that volcanic streams hosted distinct stream communities composed of more cold‐water species compared with nonvolcanic streams. Scenario analyses based on multiple global climate models and Representative Concentration Pathways (RCPs) revealed a geology‐related pattern of thermal habitat loss for cold‐water species. Nonvolcanic streams rapidly declined in thermally suitable habitats for lotic sculpins even under the lowest emission scenario (RCP 2.6). In contrast, most volcanic streams will be sustained below the thermal threshold, especially for low‐ and mid‐level emission scenarios (RCP 2.6, 4.5). However, the distinct stream community in volcanic streams and geology‐dependent habitat loss for lotic sculpins was not uniform and were more pronounced in streams with less summer precipitation or lower air temperatures. These findings highlight that underlying geology, climate variability, and their interaction should be considered simultaneously for the effective management of climate‐change refugia in mountain streams. | H84: maybe | I84: Dai | J84: no | K84: Forest | L84: no | O84: Ecological Monographs | P84: 2023 | Q84: N Ishiyama, M Sueyoshi, J García Molinos, K Iwasaki, JN. Negishi, I Koizumi, S Nagayama, A Nagasaka, Y Nagasaka, F Nakamura | R84: 10.1002/ecm.1566
B85: E444 | C85: =LEFT(B85,1) & TEXT(RIGHT(B85,LEN(B85)-1),"0000") -> E0444 | D85: E0444 | E85: forest | F85: A comprehensive overview of studies related to the ecology and genetics of fagus crenata blume (siebold's beech, japanese beech) at the species' northernmost range limit | G85: Temperate forest species, including Fagus crenata Blume, have been experiencing distributional shifts during the climate oscillation throughout the Holocene epoch. This review describes the distinctive context of F. crenata populations at the northern range from the perspective of past distribution shifts, future expansion predictions, biotic and abiotic interactions in population establishment, forest vegetation characteristics, and genetic diversity during the expansion process. The current northern distribution limit of F. crenata is in southern Hokkaido and Okushiri Islands. Since 1900, a dozen of northern limit hypotheses has advocated the presence of restriction factors; however, the species shows signs of expanding its habitat northward at present. The current northern limit is not determined by physiological limitations because of the fact that artificial plantations of F. crenata grow well beyond its range. Several studies regarding climate scenarios have predicted species persistence in the future. Sociological studies revealed that a decline in vegetation units is observed from the southern to the northern populations on the Oshima Peninsula, Hokkaido. Also, vegetation on Okushiri Island includes remnants of warm temperate flora indicating a physiographic constraint of the F. crenata forest on the island, reflecting a past distributional shift. Most of the current northern marginal populations were revealed to be established at the time of large forest disturbance. The genetic diversity of local populations has been lost during the northward distribution shift due to the founder effect in the colonizing process. Then, the gene flow from rearward populations has dwindled by the completion of the population establishment. | H85: yes | I85: Dai | J85: no | K85: Forest | L85: no | O85: Ecological Research | P85: 2023 | Q85: K Kitamura, T Matsui, M Kobayashi, K Namikawa | R85: 10.1111/1440-1703.12356
B86: E450 | C86: =LEFT(B86,1) & TEXT(RIGHT(B86,LEN(B86)-1),"0000") -> E0450 | D86: E0450 | E86: forest | F86: Changes in species, functional, and phylogenetic diversity of aculeata communities along elevational gradients in the kyushu central mountains of the japanese archipelago | G86: Climate change can degrade a community of Aculeata bees and wasps with important ecosystem roles, such as pollination and predation. In this study, we evaluated patterns in the species, functional, and phylogenetic diversity (PD) of Aculeata communities along elevational gradients in Miyazaki Prefecture, south of the Japanese archipelago. We used yellow pan traps to collect Aculeata at 200–1600 m above sea level for three seasons. We tested five functional traits (body size, trophic level, feeding guild, flight duration, and elevational range) and horizontal distribution of the species. The species diversity (SD) increased with increasing elevation. Body size, trophic level, and distribution diversity increased with increasing elevation. The community‐weighted mean trophic level and flight duration decreased with increasing elevation. PD increased with increasing elevation. The number of northern species increased with increasing elevation. Trophic structure and high seasonal segregation by shortening flight duration should promote high SD at high elevation. The results of PD suggest that geographical barriers preventing the southern species migration decreased SD at low elevations. Community degradation in the lowlands can occur with geographical barriers that limit north–south migration. We show that evaluations of functional traits and phylogeny can reveal the mechanisms underlying community assembly at our sites, where both environmental and geographical conditions affect community assembly. | H86: maybe | I86: Dai | J86: no | K86: Forest | L86: no | O86: Ecological research | P86: 2021 | Q86: K Uemori, T Mita, T Hishi | R86: 10.1111/1440-1703.12242
B87: E451 | C87: =LEFT(B87,1) & TEXT(RIGHT(B87,LEN(B87)-1),"0000") -> E0451 | D87: E0451 | E87: forest | F87: Wetlands are refuge areas that delay global warming-induced range shift of lepidoptera | G87: Lepidoptera are known to quickly respond to the increase of temperature induced by global warming. Altitudinal and latitudinal range shift are well studied processes expanding the range of warm-adapted species and contracting those of cold-adapted ones. Several models predict the colonization and extinction of above mentioned species by taking into account abiotic and biotic parameters mainly on large scale. But the effectiveness of these models is reduced by many local and microclimatic constraints. Wesuggest a primary role of wetlands as refuge areas where local extinctions and northward shift of cold-adapted species could be locally and partially delayed by the microclimate. We checked available literature and unpublished data concerning moth species assemblages of a Mediterranean area, the Italian Peninsula, where it is expected that global warming will strongly reduce the diversity of poikilothermic animals. In several cases, wetlands represent the southernmost refuge area for a large number of Eurasiatic species. Some species, usually found only at high altitude in Mediterranean areas, in wetlands are present also at low altitude. Wetlands seems thus to act such as mountains inhabiting many species largely distributed in the Euroasiatic Region, but with very scattered populations in the Mediterranean Basin. We even recorded in wetlands the presence of several Central-European species that are still unrecorded for Italian Peninsula mountains. Physical parameters which enable Mediterranean wetland to inhabit such as community are the high humidity rate that conceal summer drought, the shadow provided by trees and bushes that mitigate temperature excursions, the thermal Inversion that provide suitable habitat to cold-adapted species also at altitude lower than those usually exploited. These parameters also favor the presence of host plants supporting cold-adapted species. In conclusion, Mediterranean wetlands seem to have a great importance for conservation perspectives especially in region attaining low altitudes as they inhabit several stenotopic species. Their importance will probably increase in next decades if the previsions of a warmer world will be confirmed. Because wetlands can resist to species extinction, their presence should be evaluated for designing more predictive models of changes in species ranges induced by climate warming. | H87: maybe | I87: Dai | J87: no | K87: Forest | L87: no | O87: Handbook of nature conservation | P87: 2009 | Q87: S Scalercio, M Russo, L Dapporto | R87: https://www.researchgate.net/publication/237021968_Wetlands_are_refuge_areas_that_delay_global_warming-induced_range_shift_of_Lepidoptera
B88: E453 | C88: =LEFT(B88,1) & TEXT(RIGHT(B88,LEN(B88)-1),"0000") -> E0453 | D88: E0453 | E88: forest | F88: Molecular data and ecological niche modelling reveal a highly dynamic evolutionary history of the east asian tertiary relict cercidiphyllum (cercidiphyllaceae) | G88: East Asia’s temperate deciduous forests served as sanctuary for Tertiary relict trees, but their ages and response to past climate change remain largely unknown. To address this issue, we elucidated the evolutionary and population demographic history of Cercdiphyllum, comprising species in China/Japan (Cercdiphyllum japonicum) and central Japan (Cercdiphyllum magnificum).Fifty-three populations were genotyped using chloroplast and ribosomal DNA sequences and microsatellite loci to assess molecular structure and diversity in relation to past (Last Glacial Maximum) and present distributions based on ecological niche modelling. Late Tertiary climate cooling was reflected in a relatively recent speciation event, dated at the Mio-/Pliocene boundary. During glacials, the warm-temperate C. japonicum experienced massive habitat losses in some areas (north-central China/north Japan) but increases in others (southwest/-east China, East China Sea landbridge, south Japan). In China, the Sichuan Basin and/or the middle-Yangtze were source areas of postglacial northward recolonization; in Japan, this may have been facilitated through introgressive hybridization with the cool-temperate C. magnificum. Our findings challenge the notion of relative evolutionary and demographic stability of Tertiary relict trees, and may serve as a guideline for assessing the impact of Neogene climate change on the evolution and distribution of East Asian temperate plants. | H88: yes | I88: Fatima | J88: No | K88: Forest | L88: No | M88: Text | N88: The study only describes a qualitative northward (poleward) expansion of Cercidiphyllum after the Last Glacial Maximum and notes areas of habitat loss and gain, but it does not provide any numeric distance, elevation change, or angular bearing for the shift. | O88: New Phytologist | P88: 2012 | Q88: XS Qi, C Chen, HP Comes, S Sakaguchi, YH Liu, N Tanaka, H Sakio, YX Qiu | R88: 10.1111/j.1469-8137.2012.04242.x
